[1,["a7SABgVItKOpkJCTuyTsU9"],["_textureSetter"],["cc.SpriteFrame"],0,[[[{"name":"game-watermargin-images-luckyUI-gui-water-rank-num-bg","rect":[623,333,36,36],"offset":[0,0],"originalSize":[36,36],"capInsets":[0,0,0,0]}],[0],0,[0],[0],[0]],[[{"name":"game-watermargin-images-luckyUI-gui-water-rank-num-3","rect":[593,473,45,37],"offset":[0,0],"originalSize":[45,37],"capInsets":[0,0,0,0]}],[0],0,[0],[0],[0]],[[{"name":"game-watermargin-images-luckyUI-gui-water-rank-num-1","rect":[334,470,45,37],"offset":[0,0],"originalSize":[45,37],"capInsets":[0,0,0,0]}],[0],0,[0],[0],[0]],[[{"name":"game-watermargin-images-luckyUI-xywjtag","rect":[1,165,397,121],"offset":[0,0],"originalSize":[397,121],"capInsets":[0,0,0,0]}],[0],0,[0],[0],[0]],[[{"name":"game-watermargin-images-luckyUI-gui-water-rank-num-2","rect":[546,473,45,37],"offset":[0,0],"originalSize":[45,37],"capInsets":[0,0,0,0]}],[0],0,[0],[0],[0]]]]