[1,["ccSAou2vNEn66xwQBqZZoH"],0,[["sp.SkeletonData",["_name","_atlasText","textureNames","_skeletonJson","textures"],-1,3]],[[0,0,1,2,3,4,5]],[[0,"chicken","\r\nchicken.png\r\nsize: 454,148\r\nformat: RGBA8888\r\nfilter: Linear,Linear\r\nrepeat: none\r\nchicken/btm\r\n  rotate: true\r\n  xy: 331, 61\r\n  size: 45, 49\r\n  orig: 45, 49\r\n  offset: 0, 0\r\n  index: -1\r\nchicken/c1\r\n  rotate: false\r\n  xy: 233, 108\r\n  size: 106, 38\r\n  orig: 106, 38\r\n  offset: 0, 0\r\n  index: -1\r\nchicken/c2\r\n  rotate: false\r\n  xy: 152, 14\r\n  size: 106, 39\r\n  orig: 106, 39\r\n  offset: 0, 0\r\n  index: -1\r\nchicken/eye_Lb\r\n  rotate: true\r\n  xy: 428, 123\r\n  size: 23, 24\r\n  orig: 23, 24\r\n  offset: 0, 0\r\n  index: -1\r\nchicken/eye_Lw\r\n  rotate: false\r\n  xy: 282, 59\r\n  size: 47, 47\r\n  orig: 47, 47\r\n  offset: 0, 0\r\n  index: -1\r\nchicken/eye_Rb\r\n  rotate: false\r\n  xy: 402, 122\r\n  size: 24, 24\r\n  orig: 24, 24\r\n  offset: 0, 0\r\n  index: -1\r\nchicken/eye_Rw\r\n  rotate: true\r\n  xy: 233, 58\r\n  size: 48, 47\r\n  orig: 48, 47\r\n  offset: 0, 0\r\n  index: -1\r\nchicken/face\r\n  rotate: true\r\n  xy: 2, 19\r\n  size: 127, 75\r\n  orig: 127, 75\r\n  offset: 0, 0\r\n  index: -1\r\nchicken/face2\r\n  rotate: true\r\n  xy: 79, 14\r\n  size: 132, 71\r\n  orig: 132, 71\r\n  offset: 0, 0\r\n  index: -1\r\nchicken/light\r\n  rotate: false\r\n  xy: 152, 55\r\n  size: 79, 91\r\n  orig: 79, 91\r\n  offset: 0, 0\r\n  index: -1\r\nchicken/mouth1_3\r\n  rotate: true\r\n  xy: 326, 3\r\n  size: 54, 52\r\n  orig: 54, 52\r\n  offset: 0, 0\r\n  index: -1\r\nchicken/mouth2_3\r\n  rotate: false\r\n  xy: 260, 4\r\n  size: 64, 52\r\n  orig: 64, 52\r\n  offset: 0, 0\r\n  index: -1\r\nchicken/mouth3_2\r\n  rotate: false\r\n  xy: 380, 2\r\n  size: 68, 57\r\n  orig: 68, 57\r\n  offset: 0, 0\r\n  index: -1\r\nchicken/top\r\n  rotate: true\r\n  xy: 341, 114\r\n  size: 32, 59\r\n  orig: 32, 59\r\n  offset: 0, 0\r\n  index: -1\r\nchicken/top_b\r\n  rotate: true\r\n  xy: 382, 76\r\n  size: 36, 52\r\n  orig: 36, 52\r\n  offset: 0, 0\r\n  index: -1\r\n",["chicken.png"],{"skeleton":{"hash":"6d+jyUbeciznnV2uhPv0idL4Az8","spine":"3.6.53","width":133.99,"height":157.99,"images":"./image/"},"bones":[{"name":"root"},{"name":"chicken/top","parent":"root","length":126.78},{"name":"object/head_3","parent":"chicken/top","length":94.11},{"name":"chicken/btm","parent":"object/head_3","length":21.51,"y":-55.12},{"name":"gold_shark/eye_L","parent":"object/head_3","length":36.29,"x":34.49,"y":16.84},{"name":"chicken/eye_Lb","parent":"gold_shark/eye_L","x":-1.2,"y":-3.1,"color":"489b33ff"},{"name":"gold_shark/eye_R","parent":"object/head_3","length":46.59,"x":-34.04,"y":16.57},{"name":"chicken/eye_Rb","parent":"gold_shark/eye_R","x":-1.32,"y":-3.45,"color":"489b33ff"},{"name":"light_L","parent":"chicken/top","length":62.27,"x":34.04,"y":17.02,"color":"499e2bff"},{"name":"light_L2","parent":"chicken/top","length":62.27,"x":-34.49,"y":17.02,"color":"499e2bff"},{"name":"mouth","parent":"chicken/top","length":112.44,"y":-9.85},{"name":"up","parent":"chicken/top","length":57.8,"y":21.32}],"slots":[{"name":"chicken/top_b","bone":"up","attachment":"chicken/top_b"},{"name":"chicken/face","bone":"object/head_3","attachment":"chicken/face"},{"name":"chicken/eye_Rw","bone":"gold_shark/eye_R","attachment":"chicken/eye_Rw"},{"name":"chicken/eye_Rb","bone":"chicken/eye_Rb","attachment":"chicken/eye_Rb"},{"name":"eye_Rb_add","bone":"chicken/eye_Rb"},{"name":"chicken/eye_Lw","bone":"gold_shark/eye_L","attachment":"chicken/eye_Lw"},{"name":"chicken/eye_Lb","bone":"chicken/eye_Lb","attachment":"chicken/eye_Lb"},{"name":"eye_Lb_add","bone":"chicken/eye_Lb"},{"name":"chicken/c1","bone":"object/head_3"},{"name":"chicken/face2","bone":"object/head_3","attachment":"chicken/face2"},{"name":"chicken/btm","bone":"chicken/btm","attachment":"chicken/btm"},{"name":"chicken/top","bone":"up","attachment":"chicken/top"},{"name":"chicken/mouth1_3","bone":"mouth","attachment":"chicken/mouth1_3"},{"name":"chicken/light","bone":"light_L"},{"name":"light2","bone":"light_L2"}],"skins":{"default":{"chicken/btm":{"chicken/btm":{"type":"mesh","hull":6,"width":45,"height":49,"uvs":[1,1,0.51004,1,0,1,0,0,0.51421,0,1,0],"triangles":[1,2,3,4,1,3,4,5,0,1,4,0],"vertices":[23.28,-24.04,0.26,-24.04,-23.71,-24.04,-23.71,26.95,0.45,26.95,23.28,26.95],"edges":[4,6,0,10,6,8,8,10,0,2,2,4,8,2]}},"chicken/c1":{"chicken/c1":{"x":0.28,"y":14.83,"width":106,"height":38},"chicken/c2":{"x":0.28,"y":15.33,"width":106,"height":39}},"chicken/eye_Lb":{"chicken/eye_Lb":{"x":0.49,"y":1.1,"width":23,"height":24}},"chicken/eye_Lw":{"chicken/eye_Lw":{"x":0.29,"y":0.49,"width":47,"height":47}},"chicken/eye_Rb":{"chicken/eye_Rb":{"x":1.65,"y":1.71,"width":24,"height":24}},"chicken/eye_Rw":{"chicken/eye_Rw":{"x":-0.66,"y":0.76,"width":48,"height":47}},"chicken/face":{"chicken/face":{"type":"mesh","hull":9,"width":127,"height":75,"uvs":[1,0.86398,1,1,0,1,0,0.87214,0,0,0.41786,0,0.50153,0,0.59492,0,1,0,0.94386,0.71306,0.9004,0.24627,0.95294,0.37992,0.95877,0.53964,0.77977,0.14196,0.23691,0.14522,0.11044,0.22019,0.0579,0.35058,0.04234,0.53312,0.06179,0.71241,0.37796,0.03202,0.37215,0.22753,0.38694,0.35143,0.42638,0.49184,0.50403,0.58476,0.57799,0.5001,0.61496,0.35556,0.63592,0.22753,0.63025,0.02712],"triangles":[27,7,8,19,4,5,13,27,8,14,4,19,15,4,14,20,14,19,26,27,13,10,13,8,16,4,15,19,6,20,6,21,20,6,7,27,5,6,19,6,26,21,26,6,27,25,21,26,11,10,8,22,21,25,24,22,25,12,8,0,23,22,24,26,13,10,16,20,17,18,17,22,15,14,20,15,20,16,21,17,20,26,11,12,11,26,10,12,11,8,9,12,0,3,4,16,17,3,16,3,17,18,22,17,21,23,2,3,18,22,23,23,9,0,12,25,26,12,24,25,9,24,12,23,24,9,23,3,18,23,1,2,0,1,23],"vertices":[64.28,-11.69,64.28,-22.16,-64.71,-22.16,-64.71,-12.31,-64.71,54.83,-10.8,54.83,-0.01,54.83,12.03,54.83,64.28,54.83,57.04,-0.06,51.44,35.87,58.21,25.58,58.97,13.28,35.87,43.9,-34.15,43.65,-50.46,37.88,-57.24,27.84,-59.25,13.78,-56.74,-0.01,-15.95,52.37,-16.7,37.31,-14.79,27.77,-9.7,16.96,0.3,9.8,9.84,16.32,14.61,27.45,17.32,37.31,16.59,52.74],"edges":[2,4,2,0,0,16,18,0,20,22,22,24,24,18,20,26,14,16,12,14,8,10,10,12,28,30,30,32,32,34,34,36,4,6,6,8,36,6,10,38,38,28,38,40,40,42,42,44,44,46,46,48,50,48,52,50,14,54,54,26,52,54]}},"chicken/face2":{"chicken/face2":{"type":"mesh","hull":14,"width":132,"height":71,"uvs":[1,0.28299,1,0.40492,1,0.54408,1,1,0.72175,1,0.63635,1,0.35725,1,0.25653,1,0,1,0,0.54408,0,0.43877,0,0.31842,0,0,1,0,0.67569,0.13513,0.69816,0.23887,0.67756,0.37943,0.6401,0.50661,0.6888,0.77099,0.31605,0.14851,0.28982,0.24557,0.32541,0.39282,0.36287,0.49657,0.30668,0.7643,0.76185,0.05146,0.84341,0.03149,0.91606,0.0707,0.96223,0.15319,0.97435,0.68699,0.93646,0.79982,0.88594,0.89385,0.81963,0.95026,0.24706,0.04951,0.15549,0.0307,0.07339,0.08335,0.01972,0.20183,0.02182,0.67759,0.0534,0.77538,0.10076,0.87128,0.17128,0.94838],"triangles":[33,12,13,25,33,13,32,33,25,24,32,25,26,25,13,34,12,33,14,32,24,19,32,14,27,26,13,35,12,34,15,14,24,20,32,19,27,13,0,35,11,12,15,19,14,15,20,19,15,21,20,24,25,26,27,15,24,16,21,15,15,27,0,20,10,11,34,33,32,34,32,20,35,34,20,22,21,16,17,22,16,27,24,26,10,21,9,35,20,11,21,10,20,9,21,22,1,15,0,1,16,15,2,16,1,17,16,2,36,9,22,28,17,2,23,36,22,18,17,28,37,36,23,29,18,28,38,37,23,30,18,29,39,38,23,31,18,30,8,9,36,8,36,37,8,37,38,8,38,39,7,39,23,8,39,7,23,18,6,17,23,22,18,23,17,7,23,6,5,6,18,4,5,18,31,4,18,28,2,3,29,28,3,30,29,3,31,30,3,4,31,3],"vertices":[67.28,-18.38,67.28,-27.53,67.28,-37.96,67.28,-72.16,30,-72.16,18.55,-72.16,-18.83,-72.16,-32.33,-72.16,-66.71,-72.16,-66.71,-37.96,-66.71,-30.07,-66.71,-21.04,-66.71,2.83,67.28,2.83,23.83,-7.29,26.84,-15.07,24.08,-25.62,19.06,-35.15,25.58,-54.98,-24.36,-8.3,-27.87,-15.58,-23.1,-26.62,-18.08,-34.4,-25.61,-54.48,35.37,-1.02,46.3,0.47,56.04,-2.46,62.22,-8.65,63.85,-48.68,58.77,-57.15,52,-64.2,43.11,-68.43,-33.6,-0.87,-45.87,0.53,-56.87,-3.41,-64.06,-12.3,-63.78,-47.98,-59.55,-55.31,-53.2,-62.51,-43.76,-68.29],"edges":[24,26,28,30,30,32,32,34,34,36,36,10,38,40,40,42,42,44,44,46,10,12,46,12,28,48,48,50,50,52,52,54,0,26,54,0,0,2,2,4,4,6,4,56,56,58,58,60,60,62,6,8,8,10,62,8,38,64,64,66,66,68,68,70,22,24,70,22,20,22,16,18,18,20,18,72,72,74,74,76,76,78,12,14,14,16,78,14]}},"chicken/light":{"chicken/light":{"width":79,"height":91}},"chicken/mouth1_3":{"chicken/mouth1_3":{"type":"mesh","hull":14,"width":54,"height":52,"uvs":[1,0.31888,1,0.43884,1,1,0.56954,1,0.49339,1,0.42874,1,0,1,0,0.4671,0,0.31888,0,0,0.39714,0,0.50109,0,0.61274,0,1,0,0.87838,0.26698,0.11995,0.25899,0.92154,0.69083,0.78983,0.8863,0.0881,0.71674,0.23798,0.9075,0.49574,0.69481],"triangles":[15,9,10,14,12,13,8,9,15,14,13,0,14,0,1,7,8,15,1,20,14,11,15,10,20,15,11,7,15,20,11,12,14,20,11,14,16,20,1,18,7,20,17,20,16,19,18,20,6,7,18,6,18,19,5,19,20,4,5,20,6,19,5,20,3,4,17,3,20,16,1,2,17,16,2,3,17,2],"vertices":[28.28,7.47,28.28,0.99,28.28,-29.3,4.18,-29.3,-0.08,-29.3,-3.7,-29.3,-27.71,-29.3,-27.71,-0.53,-27.71,7.47,-27.71,24.69,-5.47,24.69,0.34,24.69,6.6,24.69,28.28,24.69,21.47,10.27,-20.99,10.7,23.89,-12.61,16.51,-23.16,-22.77,-14.01,-14.38,-24.31,0.04,-12.82],"edges":[0,26,28,0,24,26,28,24,18,20,20,30,16,18,30,16,20,22,22,24,0,2,2,4,2,32,32,34,4,6,6,8,34,6,12,14,14,16,14,36,36,38,8,10,10,12,38,10,8,40,40,22,40,2,40,14]},"chicken/mouth2_3":{"x":0.28,"y":-2.3,"width":64,"height":52},"chicken/mouth3_2":{"x":0.28,"y":-1.8,"width":68,"height":57}},"chicken/top":{"chicken/top":{"type":"mesh","hull":6,"width":32,"height":59,"uvs":[1,1,0.50494,1,0,1,0,0,0.49342,0,1,0],"triangles":[2,3,4,1,4,5,2,4,1,1,5,0],"vertices":[17.28,-9.48,0.45,-9.48,-16.71,-9.48,-16.71,51.51,0.06,51.51,17.28,51.51],"edges":[4,6,0,10,6,8,8,10,0,2,2,4,2,8]}},"chicken/top_b":{"chicken/top_b":{"type":"mesh","hull":6,"width":36,"height":52,"uvs":[1,1,0.49927,1,0,1,0,0,0.49927,0,1,0],"triangles":[1,2,3,1,4,5,1,3,4,1,5,0],"vertices":[19.28,3.51,0.26,3.51,-18.71,3.51,-18.71,57.51,0.26,57.51,19.28,57.51],"edges":[4,6,0,10,6,8,8,10,0,2,2,4,2,8]}},"eye_Lb_add":{"chicken/eye_Lb":{"x":0.49,"y":1.1,"width":23,"height":24}},"eye_Rb_add":{"chicken/eye_Rb":{"x":1.65,"y":1.71,"width":24,"height":24}},"light2":{"chicken/light":{"width":79,"height":91}}}},"animations":{"1":{"slots":{"chicken/c1":{"attachment":[{"time":0,"name":null}]},"chicken/light":{"attachment":[{"time":0,"name":null}]},"chicken/mouth1_3":{"attachment":[{"time":0,"name":"chicken/mouth1_3"}]},"eye_Lb_add":{"attachment":[{"time":0,"name":null}]},"eye_Rb_add":{"attachment":[{"time":0,"name":null}]},"light2":{"attachment":[{"time":0,"name":null}]}},"bones":{"object/head_3":{"rotate":[{"time":0,"angle":0,"curve":"stepped"},{"time":0.8667,"angle":0}],"translate":[{"time":0,"x":0,"y":0,"curve":"stepped"},{"time":0.8667,"x":0,"y":0}],"scale":[{"time":0,"x":0.954,"y":0.988,"curve":[0.128,0.21,0.532,0.87]},{"time":0.2,"x":0.938,"y":0.984,"curve":[0.543,0.13,0.505,0.86]},{"time":0.6333,"x":0.972,"y":0.992,"curve":[0.548,0.14,0.909,0.83]},{"time":0.8667,"x":0.954,"y":0.988}]},"chicken/eye_Lb":{"rotate":[{"time":0,"angle":0}],"translate":[{"time":0,"x":0,"y":0}],"scale":[{"time":0,"x":1,"y":1}]},"chicken/eye_Rb":{"rotate":[{"time":0,"angle":0}],"translate":[{"time":0,"x":0,"y":0}],"scale":[{"time":0,"x":1,"y":1}]},"light_L":{"rotate":[{"time":0,"angle":0,"curve":"stepped"},{"time":0.8667,"angle":0}],"translate":[{"time":0,"x":0,"y":0,"curve":"stepped"},{"time":0.8667,"x":0,"y":0}],"scale":[{"time":0,"x":1,"y":1,"curve":"stepped"},{"time":0.4333,"x":1,"y":1,"curve":"stepped"},{"time":0.8667,"x":1,"y":1}]},"light_L2":{"rotate":[{"time":0,"angle":0,"curve":"stepped"},{"time":0.8667,"angle":0}],"translate":[{"time":0,"x":0,"y":0,"curve":"stepped"},{"time":0.8667,"x":0,"y":0}],"scale":[{"time":0,"x":1,"y":1,"curve":"stepped"},{"time":0.4333,"x":1,"y":1,"curve":"stepped"},{"time":0.8667,"x":1,"y":1}]},"mouth":{"rotate":[{"time":0,"angle":0,"curve":"stepped"},{"time":0.8667,"angle":0}],"translate":[{"time":0,"x":0,"y":0,"curve":"stepped"},{"time":0.8667,"x":0,"y":0}],"scale":[{"time":0,"x":1,"y":1,"curve":[0.462,0.15,0.595,0.89]},{"time":0.4333,"x":1.059,"y":1,"curve":[0.503,0.13,0.525,0.84]},{"time":0.8667,"x":1,"y":1}]},"root":{"rotate":[{"time":0,"angle":0,"curve":"stepped"},{"time":0.8667,"angle":0}],"translate":[{"time":0,"x":0,"y":0,"curve":"stepped"},{"time":0.8667,"x":0,"y":0}],"scale":[{"time":0,"x":1,"y":1}]},"chicken/top":{"rotate":[{"time":0,"angle":0,"curve":"stepped"},{"time":0.8667,"angle":0}],"translate":[{"time":0,"x":0,"y":0,"curve":"stepped"},{"time":0.8667,"x":0,"y":0}],"scale":[{"time":0,"x":1,"y":1,"curve":[0.491,0.12,0.755,0.55]},{"time":0.4333,"x":1,"y":0.949,"curve":[0.496,0.12,0.491,0.86]},{"time":0.8667,"x":1,"y":1}]},"gold_shark/eye_L":{"rotate":[{"time":0,"angle":0,"curve":"stepped"},{"time":0.8667,"angle":0}],"translate":[{"time":0,"x":0,"y":0,"curve":"stepped"},{"time":0.8667,"x":0,"y":0}],"scale":[{"time":0,"x":1,"y":1,"curve":"stepped"},{"time":0.4333,"x":1,"y":1,"curve":"stepped"},{"time":0.8667,"x":1,"y":1}]},"gold_shark/eye_R":{"rotate":[{"time":0,"angle":0,"curve":"stepped"},{"time":0.8667,"angle":0}],"translate":[{"time":0,"x":0,"y":0,"curve":"stepped"},{"time":0.8667,"x":0,"y":0}],"scale":[{"time":0,"x":1,"y":1,"curve":"stepped"},{"time":0.4333,"x":1,"y":1,"curve":"stepped"},{"time":0.8667,"x":1,"y":1}]},"up":{"rotate":[{"time":0,"angle":0,"curve":"stepped"},{"time":0.8667,"angle":0}],"translate":[{"time":0,"x":0,"y":0,"curve":"stepped"},{"time":0.8667,"x":0,"y":0}],"scale":[{"time":0,"x":1,"y":1.031,"curve":[0.07,0.1,0.514,0.88]},{"time":0.2,"x":1,"y":1.068,"curve":[0.504,0.08,0.514,0.88]},{"time":0.6333,"x":1,"y":1,"curve":[0.504,0.08,0.909,0.86]},{"time":0.8667,"x":1,"y":1.031}]},"chicken/btm":{"rotate":[{"time":0,"angle":0}],"translate":[{"time":0,"x":0,"y":0}],"scale":[{"time":0,"x":1,"y":1}]}}},"2":{"slots":{"chicken/c1":{"attachment":[{"time":0,"name":null},{"time":0.3667,"name":"chicken/c1"},{"time":0.4,"name":"chicken/c2"},{"time":0.4333,"name":"chicken/c1"},{"time":0.4667,"name":null}]},"chicken/light":{"attachment":[{"time":0,"name":null}]},"chicken/mouth1_3":{"attachment":[{"time":0,"name":"chicken/mouth1_3"}]},"eye_Lb_add":{"attachment":[{"time":0,"name":null}]},"eye_Rb_add":{"attachment":[{"time":0,"name":null}]},"light2":{"attachment":[{"time":0,"name":null}]}},"bones":{"object/head_3":{"rotate":[{"time":0,"angle":0,"curve":"stepped"},{"time":0.8667,"angle":0}],"translate":[{"time":0,"x":0,"y":0,"curve":"stepped"},{"time":0.8667,"x":0,"y":0}],"scale":[{"time":0,"x":0.954,"y":0.988,"curve":[0.128,0.21,0.532,0.87]},{"time":0.2,"x":0.938,"y":0.984,"curve":[0.543,0.13,0.505,0.86]},{"time":0.6333,"x":0.972,"y":0.992,"curve":[0.548,0.14,0.909,0.83]},{"time":0.8667,"x":0.954,"y":0.988}]},"chicken/eye_Lb":{"rotate":[{"time":0,"angle":0}],"translate":[{"time":0,"x":0,"y":0}],"scale":[{"time":0,"x":1,"y":1}]},"chicken/eye_Rb":{"rotate":[{"time":0,"angle":0}],"translate":[{"time":0,"x":0,"y":0}],"scale":[{"time":0,"x":1,"y":1}]},"light_L":{"rotate":[{"time":0,"angle":0,"curve":"stepped"},{"time":0.8667,"angle":0}],"translate":[{"time":0,"x":0,"y":0,"curve":"stepped"},{"time":0.8667,"x":0,"y":0}],"scale":[{"time":0,"x":1,"y":1,"curve":"stepped"},{"time":0.4333,"x":1,"y":1,"curve":"stepped"},{"time":0.8667,"x":1,"y":1}]},"light_L2":{"rotate":[{"time":0,"angle":0,"curve":"stepped"},{"time":0.8667,"angle":0}],"translate":[{"time":0,"x":0,"y":0,"curve":"stepped"},{"time":0.8667,"x":0,"y":0}],"scale":[{"time":0,"x":1,"y":1,"curve":"stepped"},{"time":0.4333,"x":1,"y":1,"curve":"stepped"},{"time":0.8667,"x":1,"y":1}]},"mouth":{"rotate":[{"time":0,"angle":0,"curve":"stepped"},{"time":0.8667,"angle":0}],"translate":[{"time":0,"x":0,"y":0,"curve":"stepped"},{"time":0.8667,"x":0,"y":0}],"scale":[{"time":0,"x":1,"y":1,"curve":[0.462,0.15,0.595,0.89]},{"time":0.4333,"x":1.059,"y":1,"curve":[0.503,0.13,0.525,0.84]},{"time":0.8667,"x":1,"y":1}]},"root":{"rotate":[{"time":0,"angle":0,"curve":"stepped"},{"time":0.8667,"angle":0}],"translate":[{"time":0,"x":0,"y":0,"curve":"stepped"},{"time":0.8667,"x":0,"y":0}],"scale":[{"time":0,"x":1,"y":1}]},"chicken/top":{"rotate":[{"time":0,"angle":0,"curve":"stepped"},{"time":0.8667,"angle":0}],"translate":[{"time":0,"x":0,"y":0,"curve":"stepped"},{"time":0.8667,"x":0,"y":0}],"scale":[{"time":0,"x":1,"y":1,"curve":[0.491,0.12,0.755,0.55]},{"time":0.4333,"x":1,"y":0.949,"curve":[0.496,0.12,0.491,0.86]},{"time":0.8667,"x":1,"y":1}]},"gold_shark/eye_L":{"rotate":[{"time":0,"angle":0,"curve":"stepped"},{"time":0.8667,"angle":0}],"translate":[{"time":0,"x":0,"y":0,"curve":"stepped"},{"time":0.8667,"x":0,"y":0}],"scale":[{"time":0,"x":1,"y":1,"curve":"stepped"},{"time":0.4333,"x":1,"y":1,"curve":"stepped"},{"time":0.8667,"x":1,"y":1}]},"gold_shark/eye_R":{"rotate":[{"time":0,"angle":0,"curve":"stepped"},{"time":0.8667,"angle":0}],"translate":[{"time":0,"x":0,"y":0,"curve":"stepped"},{"time":0.8667,"x":0,"y":0}],"scale":[{"time":0,"x":1,"y":1,"curve":"stepped"},{"time":0.4333,"x":1,"y":1,"curve":"stepped"},{"time":0.8667,"x":1,"y":1}]},"up":{"rotate":[{"time":0,"angle":0,"curve":"stepped"},{"time":0.8667,"angle":0}],"translate":[{"time":0,"x":0,"y":0,"curve":"stepped"},{"time":0.8667,"x":0,"y":0}],"scale":[{"time":0,"x":1,"y":1.031,"curve":[0.07,0.1,0.514,0.88]},{"time":0.2,"x":1,"y":1.068,"curve":[0.504,0.08,0.514,0.88]},{"time":0.6333,"x":1,"y":1,"curve":[0.504,0.08,0.909,0.86]},{"time":0.8667,"x":1,"y":1.031}]},"chicken/btm":{"rotate":[{"time":0,"angle":0}],"translate":[{"time":0,"x":0,"y":0}],"scale":[{"time":0,"x":1,"y":1}]}}},"L1":{"slots":{"chicken/c1":{"attachment":[{"time":0,"name":null}]},"chicken/light":{"attachment":[{"time":0,"name":null}]},"chicken/mouth1_3":{"attachment":[{"time":0,"name":"chicken/mouth1_3"}]},"eye_Lb_add":{"attachment":[{"time":0,"name":null}]},"eye_Rb_add":{"attachment":[{"time":0,"name":null}]},"light2":{"attachment":[{"time":0,"name":null}]}},"bones":{"object/head_3":{"rotate":[{"time":0,"angle":0,"curve":"stepped"},{"time":0.2333,"angle":0}],"translate":[{"time":0,"x":0,"y":0,"curve":"stepped"},{"time":0.2333,"x":0,"y":0}],"scale":[{"time":0,"x":0.954,"y":0.988,"curve":"stepped"},{"time":0.2333,"x":0.954,"y":0.988}]},"chicken/eye_Lb":{"rotate":[{"time":0,"angle":0,"curve":"stepped"},{"time":0.1667,"angle":0,"curve":"stepped"},{"time":0.2333,"angle":0}],"translate":[{"time":0,"x":0,"y":0},{"time":0.1333,"x":-6.29,"y":0,"curve":[0.227,0.31,0.56,0.81]},{"time":0.2333,"x":-8.47,"y":0}],"scale":[{"time":0,"x":1,"y":1,"curve":"stepped"},{"time":0.1667,"x":1,"y":1,"curve":"stepped"},{"time":0.2333,"x":1,"y":1}]},"chicken/eye_Rb":{"rotate":[{"time":0,"angle":0,"curve":"stepped"},{"time":0.1667,"angle":0,"curve":"stepped"},{"time":0.2333,"angle":0}],"translate":[{"time":0,"x":0,"y":0},{"time":0.1333,"x":-6.29,"y":0,"curve":[0.227,0.31,0.56,0.81]},{"time":0.2333,"x":-8.47,"y":0}],"scale":[{"time":0,"x":1,"y":1,"curve":"stepped"},{"time":0.1667,"x":1,"y":1,"curve":"stepped"},{"time":0.2333,"x":1,"y":1}]},"light_L":{"rotate":[{"time":0,"angle":0,"curve":"stepped"},{"time":0.2333,"angle":0}],"translate":[{"time":0,"x":0,"y":0,"curve":"stepped"},{"time":0.2333,"x":0,"y":0}],"scale":[{"time":0,"x":1,"y":1,"curve":"stepped"},{"time":0.2333,"x":1,"y":1}]},"light_L2":{"rotate":[{"time":0,"angle":0,"curve":"stepped"},{"time":0.2333,"angle":0}],"translate":[{"time":0,"x":0,"y":0,"curve":"stepped"},{"time":0.2333,"x":0,"y":0}],"scale":[{"time":0,"x":1,"y":1,"curve":"stepped"},{"time":0.2333,"x":1,"y":1}]},"mouth":{"rotate":[{"time":0,"angle":0,"curve":"stepped"},{"time":0.2333,"angle":0}],"translate":[{"time":0,"x":0,"y":0},{"time":0.1667,"x":-2,"y":0,"curve":"stepped"},{"time":0.2333,"x":-2,"y":0}],"scale":[{"time":0,"x":1,"y":1,"curve":"stepped"},{"time":0.2333,"x":1,"y":1}]},"root":{"rotate":[{"time":0,"angle":0,"curve":"stepped"},{"time":0.2333,"angle":0}],"translate":[{"time":0,"x":0,"y":0,"curve":"stepped"},{"time":0.2333,"x":0,"y":0}],"scale":[{"time":0,"x":1,"y":1,"curve":"stepped"},{"time":0.2333,"x":1,"y":1}]},"chicken/top":{"rotate":[{"time":0,"angle":0},{"time":0.1333,"angle":2,"curve":[0.188,0.29,0.536,0.81]},{"time":0.2333,"angle":2.75}],"translate":[{"time":0,"x":0,"y":0},{"time":0.1333,"x":-2.21,"y":0,"curve":[0.129,0.17,0.579,0.81]},{"time":0.2333,"x":-3,"y":0}],"scale":[{"time":0,"x":1,"y":1,"curve":"stepped"},{"time":0.2333,"x":1,"y":1}]},"gold_shark/eye_L":{"rotate":[{"time":0,"angle":0,"curve":"stepped"},{"time":0.1667,"angle":0,"curve":"stepped"},{"time":0.2333,"angle":0}],"translate":[{"time":0,"x":0,"y":0},{"time":0.1333,"x":-3.11,"y":0.12,"curve":[0.188,0.23,0.533,0.79]},{"time":0.2333,"x":-3.12,"y":0.04}],"scale":[{"time":0,"x":1,"y":1,"curve":"stepped"},{"time":0.1,"x":1,"y":1,"curve":[0.25,0,0.75,1]},{"time":0.1667,"x":0.919,"y":1,"curve":"stepped"},{"time":0.2333,"x":0.919,"y":1}]},"gold_shark/eye_R":{"rotate":[{"time":0,"angle":0,"curve":"stepped"},{"time":0.2333,"angle":0}],"translate":[{"time":0,"x":0,"y":0},{"time":0.1333,"x":1.07,"y":1.15,"curve":[0.188,0.23,0.533,0.79]},{"time":0.2333,"x":1.08,"y":1.32}],"scale":[{"time":0,"x":1,"y":1,"curve":"stepped"},{"time":0.1,"x":1,"y":1,"curve":[0.25,0,0.75,1]},{"time":0.1667,"x":0.919,"y":1,"curve":"stepped"},{"time":0.2333,"x":0.919,"y":1}]},"up":{"rotate":[{"time":0,"angle":0},{"time":0.1333,"angle":-3.41,"curve":[0.149,0.22,0.544,0.82]},{"time":0.2333,"angle":-4.92}],"translate":[{"time":0,"x":0,"y":0,"curve":[0.504,0.08,0.514,0.88]},{"time":0.1333,"x":-0.73,"y":0,"curve":[0.149,0.22,0.544,0.82]},{"time":0.2333,"x":-1,"y":0}],"scale":[{"time":0,"x":1,"y":1.031,"curve":"stepped"},{"time":0.2333,"x":1,"y":1.031}]},"chicken/btm":{"rotate":[{"time":0,"angle":0,"curve":"stepped"},{"time":0.1667,"angle":0,"curve":"stepped"},{"time":0.2333,"angle":0}],"translate":[{"time":0,"x":0,"y":0},{"time":0.1333,"x":-1.6,"y":0,"curve":[0.133,0.19,0.532,0.8]},{"time":0.2333,"x":-2.14,"y":0}],"scale":[{"time":0,"x":1,"y":1,"curve":"stepped"},{"time":0.1667,"x":1,"y":1,"curve":"stepped"},{"time":0.2333,"x":1,"y":1}]}}},"L2":{"slots":{"chicken/c1":{"attachment":[{"time":0,"name":null}]},"chicken/light":{"attachment":[{"time":0,"name":null}]},"chicken/mouth1_3":{"attachment":[{"time":0,"name":"chicken/mouth1_3"}]},"eye_Lb_add":{"attachment":[{"time":0,"name":null}]},"eye_Rb_add":{"attachment":[{"time":0,"name":null}]},"light2":{"attachment":[{"time":0,"name":null}]}},"bones":{"object/head_3":{"rotate":[{"time":0,"angle":0}],"translate":[{"time":0,"x":0,"y":0}],"scale":[{"time":0,"x":0.954,"y":0.988},{"time":0.2,"x":0.938,"y":0.984,"curve":[0.543,0.13,0.505,0.86]},{"time":0.6333,"x":0.972,"y":0.992,"curve":[0.548,0.14,0.909,0.83]},{"time":0.8667,"x":0.954,"y":0.988}]},"chicken/eye_Lb":{"rotate":[{"time":0,"angle":0}],"translate":[{"time":0,"x":-8.47,"y":0}],"scale":[{"time":0,"x":1,"y":1}]},"chicken/eye_Rb":{"rotate":[{"time":0,"angle":0}],"translate":[{"time":0,"x":-8.47,"y":0}],"scale":[{"time":0,"x":1,"y":1}]},"light_L":{"rotate":[{"time":0,"angle":0}],"translate":[{"time":0,"x":0,"y":0}],"scale":[{"time":0,"x":1,"y":1}]},"light_L2":{"rotate":[{"time":0,"angle":0}],"translate":[{"time":0,"x":0,"y":0}],"scale":[{"time":0,"x":1,"y":1}]},"mouth":{"rotate":[{"time":0,"angle":0}],"translate":[{"time":0,"x":-2,"y":0}],"scale":[{"time":0,"x":1,"y":1},{"time":0.4333,"x":1.059,"y":1,"curve":[0.503,0.13,0.525,0.84]},{"time":0.8667,"x":1,"y":1}]},"root":{"rotate":[{"time":0,"angle":0}],"translate":[{"time":0,"x":0,"y":0}],"scale":[{"time":0,"x":1,"y":1}]},"chicken/top":{"rotate":[{"time":0,"angle":2.75}],"translate":[{"time":0,"x":-3,"y":0}],"scale":[{"time":0,"x":1,"y":1},{"time":0.4333,"x":1,"y":0.949,"curve":[0.496,0.12,0.491,0.86]},{"time":0.8667,"x":1,"y":1}]},"gold_shark/eye_L":{"rotate":[{"time":0,"angle":0}],"translate":[{"time":0,"x":-3.12,"y":0.04}],"scale":[{"time":0,"x":0.919,"y":1}]},"gold_shark/eye_R":{"rotate":[{"time":0,"angle":0}],"translate":[{"time":0,"x":1.08,"y":1.32}],"scale":[{"time":0,"x":0.919,"y":1}]},"up":{"rotate":[{"time":0,"angle":-4.92}],"translate":[{"time":0,"x":-1,"y":0}],"scale":[{"time":0,"x":1,"y":1.031},{"time":0.2,"x":1,"y":1.068,"curve":[0.504,0.08,0.514,0.88]},{"time":0.6333,"x":1,"y":1,"curve":[0.504,0.08,0.909,0.86]},{"time":0.8667,"x":1,"y":1.031}]},"chicken/btm":{"rotate":[{"time":0,"angle":0}],"translate":[{"time":0,"x":-2.14,"y":0}],"scale":[{"time":0,"x":1,"y":1}]}}},"L3":{"slots":{"chicken/c1":{"attachment":[{"time":0,"name":null},{"time":0.2,"name":null}]},"chicken/light":{"attachment":[{"time":0,"name":null},{"time":0.2,"name":null}]},"chicken/mouth1_3":{"attachment":[{"time":0,"name":"chicken/mouth1_3"},{"time":0.2,"name":"chicken/mouth1_3"}]},"eye_Lb_add":{"attachment":[{"time":0,"name":null},{"time":0.2,"name":null}]},"eye_Rb_add":{"attachment":[{"time":0,"name":null},{"time":0.2,"name":null}]},"light2":{"attachment":[{"time":0,"name":null},{"time":0.2,"name":null}]}},"bones":{"object/head_3":{"rotate":[{"time":0,"angle":0,"curve":"stepped"},{"time":0.2,"angle":0}],"translate":[{"time":0,"x":0,"y":0,"curve":"stepped"},{"time":0.2,"x":0,"y":0}],"scale":[{"time":0,"x":0.954,"y":0.988,"curve":"stepped"},{"time":0.2,"x":0.954,"y":0.988}]},"chicken/eye_Lb":{"rotate":[{"time":0,"angle":0,"curve":"stepped"},{"time":0.2,"angle":0}],"translate":[{"time":0,"x":-8.47,"y":0,"curve":[0.25,0,0.75,1]},{"time":0.2,"x":0,"y":0}],"scale":[{"time":0,"x":1,"y":1,"curve":"stepped"},{"time":0.2,"x":1,"y":1}]},"chicken/eye_Rb":{"rotate":[{"time":0,"angle":0,"curve":"stepped"},{"time":0.2,"angle":0}],"translate":[{"time":0,"x":-8.47,"y":0,"curve":[0.25,0,0.75,1]},{"time":0.2,"x":0,"y":0}],"scale":[{"time":0,"x":1,"y":1,"curve":"stepped"},{"time":0.2,"x":1,"y":1}]},"light_L":{"rotate":[{"time":0,"angle":0,"curve":"stepped"},{"time":0.2,"angle":0}],"translate":[{"time":0,"x":0,"y":0,"curve":"stepped"},{"time":0.2,"x":0,"y":0}],"scale":[{"time":0,"x":1,"y":1,"curve":"stepped"},{"time":0.2,"x":1,"y":1}]},"light_L2":{"rotate":[{"time":0,"angle":0,"curve":"stepped"},{"time":0.2,"angle":0}],"translate":[{"time":0,"x":0,"y":0,"curve":"stepped"},{"time":0.2,"x":0,"y":0}],"scale":[{"time":0,"x":1,"y":1,"curve":"stepped"},{"time":0.2,"x":1,"y":1}]},"mouth":{"rotate":[{"time":0,"angle":0,"curve":"stepped"},{"time":0.2,"angle":0}],"translate":[{"time":0,"x":-2,"y":0},{"time":0.2,"x":0,"y":0}],"scale":[{"time":0,"x":1,"y":1,"curve":"stepped"},{"time":0.2,"x":1,"y":1}]},"root":{"rotate":[{"time":0,"angle":0,"curve":"stepped"},{"time":0.2,"angle":0}],"translate":[{"time":0,"x":0,"y":0,"curve":"stepped"},{"time":0.2,"x":0,"y":0}],"scale":[{"time":0,"x":1,"y":1,"curve":"stepped"},{"time":0.2,"x":1,"y":1}]},"chicken/top":{"rotate":[{"time":0,"angle":2.75,"curve":[0.25,0,0.75,1]},{"time":0.2,"angle":0}],"translate":[{"time":0,"x":-3,"y":0,"curve":[0.25,0,0.75,1]},{"time":0.2,"x":0,"y":0}],"scale":[{"time":0,"x":1,"y":1,"curve":"stepped"},{"time":0.2,"x":1,"y":1}]},"gold_shark/eye_L":{"rotate":[{"time":0,"angle":0,"curve":"stepped"},{"time":0.2,"angle":0}],"translate":[{"time":0,"x":-3.12,"y":0.04,"curve":[0.25,0,0.75,1]},{"time":0.2,"x":0,"y":0}],"scale":[{"time":0,"x":0.919,"y":1},{"time":0.2,"x":1,"y":1}]},"gold_shark/eye_R":{"rotate":[{"time":0,"angle":0,"curve":"stepped"},{"time":0.2,"angle":0}],"translate":[{"time":0,"x":1.08,"y":1.32,"curve":[0.25,0,0.75,1]},{"time":0.2,"x":0,"y":0}],"scale":[{"time":0,"x":0.919,"y":1},{"time":0.2,"x":1,"y":1}]},"up":{"rotate":[{"time":0,"angle":-4.92,"curve":[0.25,0,0.75,1]},{"time":0.2,"angle":0}],"translate":[{"time":0,"x":-1,"y":0,"curve":[0.25,0,0.75,1]},{"time":0.2,"x":0,"y":0}],"scale":[{"time":0,"x":1,"y":1.031,"curve":"stepped"},{"time":0.2,"x":1,"y":1.031}]},"chicken/btm":{"rotate":[{"time":0,"angle":0,"curve":"stepped"},{"time":0.2,"angle":0}],"translate":[{"time":0,"x":-2.14,"y":0,"curve":[0.25,0,0.75,1]},{"time":0.2,"x":0,"y":0}],"scale":[{"time":0,"x":1,"y":1,"curve":"stepped"},{"time":0.2,"x":1,"y":1}]}}},"R1":{"slots":{"chicken/c1":{"attachment":[{"time":0,"name":null}]},"chicken/light":{"attachment":[{"time":0,"name":null}]},"chicken/mouth1_3":{"attachment":[{"time":0,"name":"chicken/mouth1_3"}]},"eye_Lb_add":{"attachment":[{"time":0,"name":null}]},"eye_Rb_add":{"attachment":[{"time":0,"name":null}]},"light2":{"attachment":[{"time":0,"name":null}]}},"bones":{"object/head_3":{"rotate":[{"time":0,"angle":0,"curve":"stepped"},{"time":0.2333,"angle":0}],"translate":[{"time":0,"x":0,"y":0,"curve":"stepped"},{"time":0.2333,"x":0,"y":0}],"scale":[{"time":0,"x":0.954,"y":0.988,"curve":"stepped"},{"time":0.2333,"x":0.954,"y":0.988}]},"chicken/eye_Lb":{"rotate":[{"time":0,"angle":0,"curve":"stepped"},{"time":0.1667,"angle":0,"curve":"stepped"},{"time":0.2333,"angle":0}],"translate":[{"time":0,"x":0,"y":0},{"time":0.1333,"x":7.16,"y":0,"curve":[0.227,0.31,0.56,0.81]},{"time":0.2333,"x":8.23,"y":0}],"scale":[{"time":0,"x":1,"y":1,"curve":"stepped"},{"time":0.1667,"x":1,"y":1,"curve":"stepped"},{"time":0.2333,"x":1,"y":1}]},"chicken/eye_Rb":{"rotate":[{"time":0,"angle":0,"curve":"stepped"},{"time":0.1667,"angle":0,"curve":"stepped"},{"time":0.2333,"angle":0}],"translate":[{"time":0,"x":0,"y":0},{"time":0.1333,"x":7.16,"y":0,"curve":[0.227,0.31,0.56,0.81]},{"time":0.2333,"x":8.23,"y":0}],"scale":[{"time":0,"x":1,"y":1,"curve":"stepped"},{"time":0.1667,"x":1,"y":1,"curve":"stepped"},{"time":0.2333,"x":1,"y":1}]},"light_L":{"rotate":[{"time":0,"angle":0,"curve":"stepped"},{"time":0.2333,"angle":0}],"translate":[{"time":0,"x":0,"y":0,"curve":"stepped"},{"time":0.2333,"x":0,"y":0}],"scale":[{"time":0,"x":1,"y":1,"curve":"stepped"},{"time":0.2333,"x":1,"y":1}]},"light_L2":{"rotate":[{"time":0,"angle":0,"curve":"stepped"},{"time":0.2333,"angle":0}],"translate":[{"time":0,"x":0,"y":0,"curve":"stepped"},{"time":0.2333,"x":0,"y":0}],"scale":[{"time":0,"x":1,"y":1,"curve":"stepped"},{"time":0.2333,"x":1,"y":1}]},"mouth":{"rotate":[{"time":0,"angle":0,"curve":"stepped"},{"time":0.2333,"angle":0}],"translate":[{"time":0,"x":0,"y":0},{"time":0.1667,"x":2,"y":0,"curve":"stepped"},{"time":0.2333,"x":2,"y":0}],"scale":[{"time":0,"x":1,"y":1,"curve":"stepped"},{"time":0.2333,"x":1,"y":1}]},"root":{"rotate":[{"time":0,"angle":0,"curve":"stepped"},{"time":0.2333,"angle":0}],"translate":[{"time":0,"x":0,"y":0,"curve":"stepped"},{"time":0.2333,"x":0,"y":0}],"scale":[{"time":0,"x":1,"y":1,"curve":"stepped"},{"time":0.2333,"x":1,"y":1}]},"chicken/top":{"rotate":[{"time":0,"angle":0},{"time":0.1333,"angle":-2.63,"curve":[0.188,0.29,0.536,0.81]},{"time":0.2333,"angle":-3.03}],"translate":[{"time":0,"x":0,"y":0},{"time":0.1333,"x":2.6,"y":0,"curve":[0.087,0.12,0.583,0.86]},{"time":0.2333,"x":3,"y":0}],"scale":[{"time":0,"x":1,"y":1,"curve":"stepped"},{"time":0.2333,"x":1,"y":1}]},"gold_shark/eye_L":{"rotate":[{"time":0,"angle":0,"curve":"stepped"},{"time":0.2333,"angle":0}],"translate":[{"time":0,"x":0,"y":0},{"time":0.1333,"x":-1.79,"y":0.58,"curve":[0.188,0.23,0.533,0.79]},{"time":0.2333,"x":-2.05,"y":0.66}],"scale":[{"time":0,"x":1,"y":1},{"time":0.1667,"x":0.919,"y":1,"curve":"stepped"},{"time":0.2333,"x":0.919,"y":1}]},"gold_shark/eye_R":{"rotate":[{"time":0,"angle":0,"curve":"stepped"},{"time":0.2333,"angle":0}],"translate":[{"time":0,"x":0,"y":0},{"time":0.1333,"x":1.9,"y":0.04,"curve":[0.188,0.23,0.533,0.79]},{"time":0.2333,"x":2.03,"y":0.05}],"scale":[{"time":0,"x":1,"y":1},{"time":0.1667,"x":0.919,"y":1,"curve":"stepped"},{"time":0.2333,"x":0.919,"y":1}]},"up":{"rotate":[{"time":0,"angle":0},{"time":0.1333,"angle":5.78,"curve":[0.149,0.22,0.544,0.82]},{"time":0.2333,"angle":6.64}],"translate":[{"time":0,"x":0,"y":0,"curve":[0.504,0.08,0.514,0.88]},{"time":0.1333,"x":0.86,"y":0,"curve":[0.149,0.22,0.544,0.82]},{"time":0.2333,"x":1,"y":0}],"scale":[{"time":0,"x":1,"y":1.031,"curve":"stepped"},{"time":0.2333,"x":1,"y":1.031}]},"chicken/btm":{"rotate":[{"time":0,"angle":0,"curve":"stepped"},{"time":0.1667,"angle":0,"curve":"stepped"},{"time":0.2333,"angle":0}],"translate":[{"time":0,"x":0,"y":0},{"time":0.1333,"x":1.79,"y":0,"curve":[0.133,0.19,0.532,0.8]},{"time":0.2333,"x":2.05,"y":0}],"scale":[{"time":0,"x":1,"y":1,"curve":"stepped"},{"time":0.1667,"x":1,"y":1,"curve":"stepped"},{"time":0.2333,"x":1,"y":1}]}}},"R2":{"slots":{"chicken/c1":{"attachment":[{"time":0,"name":null}]},"chicken/light":{"attachment":[{"time":0,"name":null}]},"chicken/mouth1_3":{"attachment":[{"time":0,"name":"chicken/mouth1_3"}]},"eye_Lb_add":{"attachment":[{"time":0,"name":null}]},"eye_Rb_add":{"attachment":[{"time":0,"name":null}]},"light2":{"attachment":[{"time":0,"name":null}]}},"bones":{"object/head_3":{"rotate":[{"time":0,"angle":0}],"translate":[{"time":0,"x":0,"y":0}],"scale":[{"time":0,"x":0.954,"y":0.988},{"time":0.2,"x":0.938,"y":0.984,"curve":[0.543,0.13,0.505,0.86]},{"time":0.6333,"x":0.972,"y":0.992,"curve":[0.548,0.14,0.909,0.83]},{"time":0.8667,"x":0.954,"y":0.988}]},"chicken/eye_Lb":{"rotate":[{"time":0,"angle":0}],"translate":[{"time":0,"x":8.23,"y":0}],"scale":[{"time":0,"x":1,"y":1}]},"chicken/eye_Rb":{"rotate":[{"time":0,"angle":0}],"translate":[{"time":0,"x":8.23,"y":0}],"scale":[{"time":0,"x":1,"y":1}]},"light_L":{"rotate":[{"time":0,"angle":0}],"translate":[{"time":0,"x":0,"y":0}],"scale":[{"time":0,"x":1,"y":1}]},"light_L2":{"rotate":[{"time":0,"angle":0}],"translate":[{"time":0,"x":0,"y":0}],"scale":[{"time":0,"x":1,"y":1}]},"mouth":{"rotate":[{"time":0,"angle":0}],"translate":[{"time":0,"x":2,"y":0}],"scale":[{"time":0,"x":1,"y":1},{"time":0.4333,"x":1.059,"y":1,"curve":[0.503,0.13,0.525,0.84]},{"time":0.8667,"x":1,"y":1}]},"root":{"rotate":[{"time":0,"angle":0}],"translate":[{"time":0,"x":0,"y":0}],"scale":[{"time":0,"x":1,"y":1}]},"chicken/top":{"rotate":[{"time":0,"angle":-3.03}],"translate":[{"time":0,"x":3,"y":0}],"scale":[{"time":0,"x":1,"y":1},{"time":0.4333,"x":1,"y":0.949,"curve":[0.496,0.12,0.491,0.86]},{"time":0.8667,"x":1,"y":1}]},"gold_shark/eye_L":{"rotate":[{"time":0,"angle":0}],"translate":[{"time":0,"x":-2.05,"y":0.66}],"scale":[{"time":0,"x":0.919,"y":1}]},"gold_shark/eye_R":{"rotate":[{"time":0,"angle":0}],"translate":[{"time":0,"x":2.03,"y":0.05}],"scale":[{"time":0,"x":0.919,"y":1}]},"up":{"rotate":[{"time":0,"angle":6.64}],"translate":[{"time":0,"x":1,"y":0}],"scale":[{"time":0,"x":1,"y":1.031},{"time":0.2,"x":1,"y":1.068,"curve":[0.504,0.08,0.514,0.88]},{"time":0.6333,"x":1,"y":1,"curve":[0.504,0.08,0.909,0.86]},{"time":0.8667,"x":1,"y":1.031}]},"chicken/btm":{"rotate":[{"time":0,"angle":0}],"translate":[{"time":0,"x":2.05,"y":0}],"scale":[{"time":0,"x":1,"y":1}]}}},"R3":{"slots":{"chicken/c1":{"attachment":[{"time":0,"name":null},{"time":0.2,"name":null}]},"chicken/light":{"attachment":[{"time":0,"name":null},{"time":0.2,"name":null}]},"chicken/mouth1_3":{"attachment":[{"time":0,"name":"chicken/mouth1_3"},{"time":0.2,"name":"chicken/mouth1_3"}]},"eye_Lb_add":{"attachment":[{"time":0,"name":null},{"time":0.2,"name":null}]},"eye_Rb_add":{"attachment":[{"time":0,"name":null},{"time":0.2,"name":null}]},"light2":{"attachment":[{"time":0,"name":null},{"time":0.2,"name":null}]}},"bones":{"object/head_3":{"rotate":[{"time":0,"angle":0,"curve":"stepped"},{"time":0.2,"angle":0}],"translate":[{"time":0,"x":0,"y":0,"curve":"stepped"},{"time":0.2,"x":0,"y":0}],"scale":[{"time":0,"x":0.954,"y":0.988,"curve":"stepped"},{"time":0.2,"x":0.954,"y":0.988}]},"chicken/eye_Lb":{"rotate":[{"time":0,"angle":0,"curve":"stepped"},{"time":0.2,"angle":0}],"translate":[{"time":0,"x":8.23,"y":0,"curve":[0.25,0,0.75,1]},{"time":0.2,"x":0,"y":0}],"scale":[{"time":0,"x":1,"y":1,"curve":"stepped"},{"time":0.2,"x":1,"y":1}]},"chicken/eye_Rb":{"rotate":[{"time":0,"angle":0,"curve":"stepped"},{"time":0.2,"angle":0}],"translate":[{"time":0,"x":8.23,"y":0,"curve":[0.25,0,0.75,1]},{"time":0.2,"x":0,"y":0}],"scale":[{"time":0,"x":1,"y":1,"curve":"stepped"},{"time":0.2,"x":1,"y":1}]},"light_L":{"rotate":[{"time":0,"angle":0,"curve":"stepped"},{"time":0.2,"angle":0}],"translate":[{"time":0,"x":0,"y":0,"curve":"stepped"},{"time":0.2,"x":0,"y":0}],"scale":[{"time":0,"x":1,"y":1,"curve":"stepped"},{"time":0.2,"x":1,"y":1}]},"light_L2":{"rotate":[{"time":0,"angle":0,"curve":"stepped"},{"time":0.2,"angle":0}],"translate":[{"time":0,"x":0,"y":0,"curve":"stepped"},{"time":0.2,"x":0,"y":0}],"scale":[{"time":0,"x":1,"y":1,"curve":"stepped"},{"time":0.2,"x":1,"y":1}]},"mouth":{"rotate":[{"time":0,"angle":0,"curve":"stepped"},{"time":0.2,"angle":0}],"translate":[{"time":0,"x":2,"y":0},{"time":0.2,"x":0,"y":0}],"scale":[{"time":0,"x":1,"y":1,"curve":"stepped"},{"time":0.2,"x":1,"y":1}]},"root":{"rotate":[{"time":0,"angle":0,"curve":"stepped"},{"time":0.2,"angle":0}],"translate":[{"time":0,"x":0,"y":0,"curve":"stepped"},{"time":0.2,"x":0,"y":0}],"scale":[{"time":0,"x":1,"y":1,"curve":"stepped"},{"time":0.2,"x":1,"y":1}]},"chicken/top":{"rotate":[{"time":0,"angle":-3.03,"curve":[0.25,0,0.75,1]},{"time":0.2,"angle":0}],"translate":[{"time":0,"x":3,"y":0,"curve":[0.25,0,0.75,1]},{"time":0.2,"x":0,"y":0}],"scale":[{"time":0,"x":1,"y":1,"curve":"stepped"},{"time":0.2,"x":1,"y":1}]},"gold_shark/eye_L":{"rotate":[{"time":0,"angle":0,"curve":"stepped"},{"time":0.2,"angle":0}],"translate":[{"time":0,"x":-2.05,"y":0.66,"curve":[0.25,0,0.75,1]},{"time":0.2,"x":0,"y":0}],"scale":[{"time":0,"x":0.919,"y":1},{"time":0.2,"x":1,"y":1}]},"gold_shark/eye_R":{"rotate":[{"time":0,"angle":0,"curve":"stepped"},{"time":0.2,"angle":0}],"translate":[{"time":0,"x":2.03,"y":0.05,"curve":[0.25,0,0.75,1]},{"time":0.2,"x":0,"y":0}],"scale":[{"time":0,"x":0.919,"y":1},{"time":0.2,"x":1,"y":1}]},"up":{"rotate":[{"time":0,"angle":6.64,"curve":[0.25,0,0.75,1]},{"time":0.2,"angle":0}],"translate":[{"time":0,"x":1,"y":0,"curve":[0.25,0,0.75,1]},{"time":0.2,"x":0,"y":0}],"scale":[{"time":0,"x":1,"y":1.031,"curve":"stepped"},{"time":0.2,"x":1,"y":1.031}]},"chicken/btm":{"rotate":[{"time":0,"angle":0,"curve":"stepped"},{"time":0.2,"angle":0}],"translate":[{"time":0,"x":2.05,"y":0,"curve":[0.25,0,0.75,1]},{"time":0.2,"x":0,"y":0}],"scale":[{"time":0,"x":1,"y":1,"curve":"stepped"},{"time":0.2,"x":1,"y":1}]}}},"animation":{"slots":{"chicken/c1":{"attachment":[{"time":0,"name":null},{"time":0.0667,"name":"chicken/c1"},{"time":0.1,"name":"chicken/c2"},{"time":0.2,"name":"chicken/c1"},{"time":0.2333,"name":null},{"time":0.7,"name":"chicken/c1"},{"time":0.7333,"name":"chicken/c2"},{"time":0.8333,"name":"chicken/c1"},{"time":0.8667,"name":null}]},"chicken/eye_Lb":{"attachment":[{"time":0,"name":"chicken/eye_Lb"},{"time":0.1667,"name":"chicken/eye_Lb"}]},"chicken/eye_Rb":{"attachment":[{"time":0,"name":"chicken/eye_Rb"},{"time":0.1667,"name":"chicken/eye_Rb"}]},"chicken/light":{"attachment":[{"time":0,"name":null}]},"chicken/mouth1_3":{"attachment":[{"time":0,"name":"chicken/mouth1_3"},{"time":0.1667,"name":"chicken/mouth1_3"},{"time":0.2,"name":"chicken/mouth2_3"},{"time":0.2333,"name":"chicken/mouth3_2"},{"time":0.6333,"name":"chicken/mouth3_2"},{"time":0.6667,"name":"chicken/mouth2_3"},{"time":0.7,"name":"chicken/mouth1_3"}]},"eye_Lb_add":{"attachment":[{"time":0,"name":null},{"time":0.1667,"name":"chicken/eye_Lb"},{"time":0.7333,"name":null}]},"eye_Rb_add":{"attachment":[{"time":0,"name":null},{"time":0.1667,"name":"chicken/eye_Rb"},{"time":0.7333,"name":null}]},"light2":{"attachment":[{"time":0,"name":null}]}},"bones":{"object/head_3":{"rotate":[{"time":0,"angle":0}],"translate":[{"time":0,"x":0,"y":0}],"scale":[{"time":0,"x":0.954,"y":0.988}]},"light_L":{"rotate":[{"time":0,"angle":0}],"translate":[{"time":0,"x":0,"y":0}],"scale":[{"time":0,"x":1,"y":1}]},"light_L2":{"rotate":[{"time":0,"angle":0}],"translate":[{"time":0,"x":0,"y":0}],"scale":[{"time":0,"x":1,"y":1}]},"mouth":{"rotate":[{"time":0,"angle":0}],"translate":[{"time":0,"x":0,"y":0}],"scale":[{"time":0,"x":1,"y":1,"curve":[0.453,0.14,0.722,0.6]},{"time":0.1333,"x":1.219,"y":0.951,"curve":[0.25,0,0.75,1]},{"time":0.2333,"x":1.132,"y":1.296,"curve":[0.25,0,0.75,1]},{"time":0.3333,"x":1.225,"y":0.884,"curve":[0.25,0,0.75,1]},{"time":0.4333,"x":1.132,"y":1.296,"curve":[0.25,0,0.75,1]},{"time":0.5333,"x":1.225,"y":0.884,"curve":[0.25,0,0.75,1]},{"time":0.6333,"x":1.132,"y":1.296,"curve":[0.25,0,0.75,1]},{"time":0.7,"x":1,"y":1}]},"chicken/top":{"rotate":[{"time":0,"angle":0}],"translate":[{"time":0,"x":0,"y":0,"curve":[0.25,0,0.75,1]},{"time":0.1667,"x":0,"y":-5,"curve":[0.25,0,0.75,1]},{"time":0.3,"x":0,"y":9,"curve":[0.25,0,0.75,1]},{"time":0.4667,"x":0,"y":12,"curve":[0.25,0,0.75,1]},{"time":0.6333,"x":0,"y":-5,"curve":[0.25,0,0.75,1]},{"time":0.8,"x":0,"y":4,"curve":[0.25,0,0.75,1]},{"time":1,"x":0,"y":0}],"scale":[{"time":0,"x":1,"y":1,"curve":[0.25,0,0.75,1]},{"time":0.1333,"x":1.12,"y":0.832,"curve":[0.25,0,0.75,1]},{"time":0.3,"x":0.919,"y":1.051,"curve":[0.25,0,0.75,1]},{"time":0.4667,"x":1.058,"y":1,"curve":[0.25,0,0.75,1]},{"time":0.6,"x":0.932,"y":1.017,"curve":[0.25,0,0.75,1]},{"time":0.7333,"x":1.087,"y":0.799,"curve":[0.25,0,0.75,1]},{"time":0.9333,"x":1,"y":1}]},"gold_shark/eye_L":{"rotate":[{"time":0,"angle":0}],"translate":[{"time":0,"x":0,"y":0}],"scale":[{"time":0,"x":1,"y":1}]},"up":{"rotate":[{"time":0,"angle":0}],"translate":[{"time":0,"x":0,"y":0}],"scale":[{"time":0,"x":1,"y":1.031,"curve":[0.07,0.1,0.514,0.88]},{"time":0.1667,"x":1.073,"y":0.926},{"time":0.3333,"x":1.031,"y":1.03},{"time":0.5667,"x":1,"y":1.052},{"time":0.7667,"x":1.04,"y":0.986},{"time":1,"x":1,"y":1.031}]},"root":{"rotate":[{"time":0,"angle":0}],"translate":[{"time":0,"x":0,"y":0}],"scale":[{"time":0,"x":1,"y":1}]},"gold_shark/eye_R":{"rotate":[{"time":0,"angle":0}],"translate":[{"time":0,"x":0,"y":0}],"scale":[{"time":0,"x":1,"y":1}]}}},"down1":{"slots":{"chicken/c1":{"attachment":[{"time":0,"name":null}]},"chicken/light":{"attachment":[{"time":0,"name":null}]},"chicken/mouth1_3":{"attachment":[{"time":0,"name":"chicken/mouth1_3"}]},"eye_Lb_add":{"attachment":[{"time":0,"name":null}]},"eye_Rb_add":{"attachment":[{"time":0,"name":null}]},"light2":{"attachment":[{"time":0,"name":null}]}},"bones":{"object/head_3":{"rotate":[{"time":0,"angle":0,"curve":"stepped"},{"time":0.2333,"angle":0}],"translate":[{"time":0,"x":0,"y":0},{"time":0.1333,"x":0,"y":0.99,"curve":[0.159,0.19,0.545,0.77]},{"time":0.2333,"x":0,"y":2}],"scale":[{"time":0,"x":0.954,"y":0.988,"curve":"stepped"},{"time":0.2333,"x":0.954,"y":0.988}]},"chicken/eye_Lb":{"rotate":[{"time":0,"angle":0,"curve":"stepped"},{"time":0.2333,"angle":0}],"translate":[{"time":0,"x":0,"y":0},{"time":0.1333,"x":0,"y":-3.49,"curve":[0.131,0.18,0.495,0.83]},{"time":0.2333,"x":0,"y":-6.11}],"scale":[{"time":0,"x":1,"y":1,"curve":"stepped"},{"time":0.2333,"x":1,"y":1}]},"chicken/eye_Rb":{"rotate":[{"time":0,"angle":0,"curve":"stepped"},{"time":0.2333,"angle":0}],"translate":[{"time":0,"x":0,"y":0},{"time":0.1333,"x":0,"y":-3.49,"curve":[0.131,0.18,0.495,0.83]},{"time":0.2333,"x":0,"y":-6.11}],"scale":[{"time":0,"x":1,"y":1,"curve":"stepped"},{"time":0.2333,"x":1,"y":1}]},"light_L":{"rotate":[{"time":0,"angle":0,"curve":"stepped"},{"time":0.2333,"angle":0}],"translate":[{"time":0,"x":0,"y":0,"curve":"stepped"},{"time":0.2333,"x":0,"y":0}],"scale":[{"time":0,"x":1,"y":1,"curve":"stepped"},{"time":0.2333,"x":1,"y":1}]},"light_L2":{"rotate":[{"time":0,"angle":0,"curve":"stepped"},{"time":0.2333,"angle":0}],"translate":[{"time":0,"x":0,"y":0,"curve":"stepped"},{"time":0.2333,"x":0,"y":0}],"scale":[{"time":0,"x":1,"y":1,"curve":"stepped"},{"time":0.2333,"x":1,"y":1}]},"mouth":{"rotate":[{"time":0,"angle":0,"curve":"stepped"},{"time":0.2333,"angle":0}],"translate":[{"time":0,"x":0,"y":0},{"time":0.1333,"x":0,"y":-0.99,"curve":[0.181,0.19,0.654,0.84]},{"time":0.2333,"x":0,"y":-2}],"scale":[{"time":0,"x":1,"y":1,"curve":"stepped"},{"time":0.2333,"x":1,"y":1}]},"root":{"rotate":[{"time":0,"angle":0,"curve":"stepped"},{"time":0.2333,"angle":0}],"translate":[{"time":0,"x":0,"y":0,"curve":"stepped"},{"time":0.2333,"x":0,"y":0}],"scale":[{"time":0,"x":1,"y":1,"curve":"stepped"},{"time":0.2333,"x":1,"y":1}]},"chicken/top":{"rotate":[{"time":0,"angle":0,"curve":"stepped"},{"time":0.2333,"angle":0}],"translate":[{"time":0,"x":0,"y":0,"curve":"stepped"},{"time":0.2333,"x":0,"y":0}],"scale":[{"time":0,"x":1,"y":1,"curve":"stepped"},{"time":0.2333,"x":1,"y":1}]},"gold_shark/eye_L":{"rotate":[{"time":0,"angle":0,"curve":"stepped"},{"time":0.2333,"angle":0}],"translate":[{"time":0,"x":0,"y":0},{"time":0.1667,"x":0,"y":-5.11,"curve":"stepped"},{"time":0.2333,"x":0,"y":-5.11}],"scale":[{"time":0,"x":1,"y":1,"curve":"stepped"},{"time":0.1,"x":1,"y":1,"curve":[0.204,0.26,0.704,0.85]},{"time":0.1667,"x":1,"y":0.91,"curve":"stepped"},{"time":0.2333,"x":1,"y":0.91}]},"gold_shark/eye_R":{"rotate":[{"time":0,"angle":0,"curve":"stepped"},{"time":0.2333,"angle":0}],"translate":[{"time":0,"x":0,"y":0},{"time":0.1667,"x":0,"y":-5.11,"curve":"stepped"},{"time":0.2333,"x":0,"y":-5.11}],"scale":[{"time":0,"x":1,"y":1,"curve":"stepped"},{"time":0.1,"x":1,"y":1,"curve":[0.204,0.26,0.704,0.85]},{"time":0.1667,"x":1,"y":0.91,"curve":"stepped"},{"time":0.2333,"x":1,"y":0.91}]},"up":{"rotate":[{"time":0,"angle":0,"curve":"stepped"},{"time":0.2333,"angle":0}],"translate":[{"time":0,"x":0,"y":0,"curve":[0.504,0.08,0.514,0.88]},{"time":0.1333,"x":0,"y":-2.12,"curve":[0.109,0.15,0.49,0.8]},{"time":0.2333,"x":0,"y":-2}],"scale":[{"time":0,"x":1,"y":1.031,"curve":"stepped"},{"time":0.2333,"x":1,"y":1.031}]},"chicken/btm":{"rotate":[{"time":0,"angle":0,"curve":"stepped"},{"time":0.1667,"angle":0,"curve":"stepped"},{"time":0.2333,"angle":0}],"translate":[{"time":0,"x":0,"y":0},{"time":0.1333,"x":0,"y":-2.02,"curve":[0.131,0.18,0.604,0.79]},{"time":0.2333,"x":0,"y":-4.07}],"scale":[{"time":0,"x":1,"y":1,"curve":"stepped"},{"time":0.1667,"x":1,"y":1,"curve":"stepped"},{"time":0.2333,"x":1,"y":1}]}}},"down2":{"slots":{"chicken/c1":{"attachment":[{"time":0,"name":null}]},"chicken/light":{"attachment":[{"time":0,"name":null}]},"chicken/mouth1_3":{"attachment":[{"time":0,"name":"chicken/mouth1_3"}]},"eye_Lb_add":{"attachment":[{"time":0,"name":null}]},"eye_Rb_add":{"attachment":[{"time":0,"name":null}]},"light2":{"attachment":[{"time":0,"name":null}]}},"bones":{"object/head_3":{"rotate":[{"time":0,"angle":0}],"translate":[{"time":0,"x":0,"y":2}],"scale":[{"time":0,"x":0.954,"y":0.988},{"time":0.2,"x":0.938,"y":0.984,"curve":[0.543,0.13,0.505,0.86]},{"time":0.6333,"x":0.972,"y":0.992,"curve":[0.548,0.14,0.909,0.83]},{"time":0.8667,"x":0.954,"y":0.988}]},"chicken/eye_Lb":{"rotate":[{"time":0,"angle":0}],"translate":[{"time":0,"x":0,"y":-6.11}],"scale":[{"time":0,"x":1,"y":1}]},"chicken/eye_Rb":{"rotate":[{"time":0,"angle":0}],"translate":[{"time":0,"x":0,"y":-6.11}],"scale":[{"time":0,"x":1,"y":1}]},"light_L":{"rotate":[{"time":0,"angle":0}],"translate":[{"time":0,"x":0,"y":0}],"scale":[{"time":0,"x":1,"y":1}]},"light_L2":{"rotate":[{"time":0,"angle":0}],"translate":[{"time":0,"x":0,"y":0}],"scale":[{"time":0,"x":1,"y":1}]},"mouth":{"rotate":[{"time":0,"angle":0}],"translate":[{"time":0,"x":0,"y":-2}],"scale":[{"time":0,"x":1,"y":1},{"time":0.4333,"x":1.059,"y":1,"curve":[0.503,0.13,0.525,0.84]},{"time":0.8667,"x":1,"y":1}]},"root":{"rotate":[{"time":0,"angle":0}],"translate":[{"time":0,"x":0,"y":0}],"scale":[{"time":0,"x":1,"y":1}]},"chicken/top":{"rotate":[{"time":0,"angle":0}],"translate":[{"time":0,"x":0,"y":0}],"scale":[{"time":0,"x":1,"y":1},{"time":0.4333,"x":1,"y":0.949,"curve":[0.496,0.12,0.491,0.86]},{"time":0.8667,"x":1,"y":1}]},"gold_shark/eye_L":{"rotate":[{"time":0,"angle":0}],"translate":[{"time":0,"x":0,"y":-5.11}],"scale":[{"time":0,"x":1,"y":0.91}]},"gold_shark/eye_R":{"rotate":[{"time":0,"angle":0}],"translate":[{"time":0,"x":0,"y":-5.11}],"scale":[{"time":0,"x":1,"y":0.91}]},"up":{"rotate":[{"time":0,"angle":0}],"translate":[{"time":0,"x":0,"y":-2}],"scale":[{"time":0,"x":1,"y":1.031},{"time":0.2,"x":1,"y":1.068,"curve":[0.504,0.08,0.514,0.88]},{"time":0.6333,"x":1,"y":1,"curve":[0.504,0.08,0.909,0.86]},{"time":0.8667,"x":1,"y":1.031}]},"chicken/btm":{"rotate":[{"time":0,"angle":0}],"translate":[{"time":0,"x":0,"y":-4.07}],"scale":[{"time":0,"x":1,"y":1}]}}},"down3":{"slots":{"chicken/c1":{"attachment":[{"time":0,"name":null},{"time":0.2,"name":null}]},"chicken/light":{"attachment":[{"time":0,"name":null},{"time":0.2,"name":null}]},"chicken/mouth1_3":{"attachment":[{"time":0,"name":"chicken/mouth1_3"},{"time":0.2,"name":"chicken/mouth1_3"}]},"eye_Lb_add":{"attachment":[{"time":0,"name":null},{"time":0.2,"name":null}]},"eye_Rb_add":{"attachment":[{"time":0,"name":null},{"time":0.2,"name":null}]},"light2":{"attachment":[{"time":0,"name":null},{"time":0.2,"name":null}]}},"bones":{"object/head_3":{"rotate":[{"time":0,"angle":0,"curve":"stepped"},{"time":0.2,"angle":0}],"translate":[{"time":0,"x":0,"y":2,"curve":[0.25,0,0.75,1]},{"time":0.2,"x":0,"y":0}],"scale":[{"time":0,"x":0.954,"y":0.988,"curve":"stepped"},{"time":0.2,"x":0.954,"y":0.988}]},"chicken/eye_Lb":{"rotate":[{"time":0,"angle":0,"curve":"stepped"},{"time":0.2,"angle":0}],"translate":[{"time":0,"x":0,"y":-6.11,"curve":[0.25,0,0.75,1]},{"time":0.2,"x":0,"y":0}],"scale":[{"time":0,"x":1,"y":1,"curve":"stepped"},{"time":0.2,"x":1,"y":1}]},"chicken/eye_Rb":{"rotate":[{"time":0,"angle":0,"curve":"stepped"},{"time":0.2,"angle":0}],"translate":[{"time":0,"x":0,"y":-6.11,"curve":[0.25,0,0.75,1]},{"time":0.2,"x":0,"y":0}],"scale":[{"time":0,"x":1,"y":1,"curve":"stepped"},{"time":0.2,"x":1,"y":1}]},"light_L":{"rotate":[{"time":0,"angle":0,"curve":"stepped"},{"time":0.2,"angle":0}],"translate":[{"time":0,"x":0,"y":0,"curve":"stepped"},{"time":0.2,"x":0,"y":0}],"scale":[{"time":0,"x":1,"y":1,"curve":"stepped"},{"time":0.2,"x":1,"y":1}]},"light_L2":{"rotate":[{"time":0,"angle":0,"curve":"stepped"},{"time":0.2,"angle":0}],"translate":[{"time":0,"x":0,"y":0,"curve":"stepped"},{"time":0.2,"x":0,"y":0}],"scale":[{"time":0,"x":1,"y":1,"curve":"stepped"},{"time":0.2,"x":1,"y":1}]},"mouth":{"rotate":[{"time":0,"angle":0,"curve":"stepped"},{"time":0.2,"angle":0}],"translate":[{"time":0,"x":0,"y":-2,"curve":[0.25,0,0.75,1]},{"time":0.2,"x":0,"y":0}],"scale":[{"time":0,"x":1,"y":1,"curve":"stepped"},{"time":0.2,"x":1,"y":1}]},"root":{"rotate":[{"time":0,"angle":0,"curve":"stepped"},{"time":0.2,"angle":0}],"translate":[{"time":0,"x":0,"y":0,"curve":"stepped"},{"time":0.2,"x":0,"y":0}],"scale":[{"time":0,"x":1,"y":1,"curve":"stepped"},{"time":0.2,"x":1,"y":1}]},"chicken/top":{"rotate":[{"time":0,"angle":0,"curve":"stepped"},{"time":0.2,"angle":0}],"translate":[{"time":0,"x":0,"y":0,"curve":"stepped"},{"time":0.2,"x":0,"y":0}],"scale":[{"time":0,"x":1,"y":1,"curve":"stepped"},{"time":0.2,"x":1,"y":1}]},"gold_shark/eye_L":{"rotate":[{"time":0,"angle":0,"curve":"stepped"},{"time":0.2,"angle":0}],"translate":[{"time":0,"x":0,"y":-5.11,"curve":[0.271,0.09,0.752,1]},{"time":0.2,"x":0,"y":0}],"scale":[{"time":0,"x":1,"y":0.91,"curve":[0.271,0.09,0.752,1]},{"time":0.2,"x":1,"y":1}]},"gold_shark/eye_R":{"rotate":[{"time":0,"angle":0,"curve":"stepped"},{"time":0.2,"angle":0}],"translate":[{"time":0,"x":0,"y":-5.11,"curve":[0.271,0.09,0.752,1]},{"time":0.2,"x":0,"y":0}],"scale":[{"time":0,"x":1,"y":0.91,"curve":[0.271,0.09,0.752,1]},{"time":0.2,"x":1,"y":1}]},"up":{"rotate":[{"time":0,"angle":0,"curve":"stepped"},{"time":0.2,"angle":0}],"translate":[{"time":0,"x":0,"y":-2,"curve":[0.25,0,0.75,1]},{"time":0.2,"x":0,"y":0}],"scale":[{"time":0,"x":1,"y":1.031,"curve":"stepped"},{"time":0.2,"x":1,"y":1.031}]},"chicken/btm":{"rotate":[{"time":0,"angle":0,"curve":"stepped"},{"time":0.2,"angle":0}],"translate":[{"time":0,"x":0,"y":-4.07,"curve":[0.25,0,0.75,1]},{"time":0.2,"x":0,"y":0}],"scale":[{"time":0,"x":1,"y":1,"curve":"stepped"},{"time":0.2,"x":1,"y":1}]}}},"up1":{"slots":{"chicken/c1":{"attachment":[{"time":0,"name":null}]},"chicken/light":{"attachment":[{"time":0,"name":null}]},"chicken/mouth1_3":{"attachment":[{"time":0,"name":"chicken/mouth1_3"}]},"eye_Lb_add":{"attachment":[{"time":0,"name":null}]},"eye_Rb_add":{"attachment":[{"time":0,"name":null}]},"light2":{"attachment":[{"time":0,"name":null}]}},"bones":{"object/head_3":{"rotate":[{"time":0,"angle":0,"curve":"stepped"},{"time":0.2333,"angle":0}],"translate":[{"time":0,"x":0,"y":0},{"time":0.1333,"x":0,"y":-2.83,"curve":[0.159,0.19,0.545,0.77]},{"time":0.2333,"x":0,"y":-3.06}],"scale":[{"time":0,"x":0.954,"y":0.988,"curve":"stepped"},{"time":0.2333,"x":0.954,"y":0.988}]},"chicken/eye_Lb":{"rotate":[{"time":0,"angle":0,"curve":"stepped"},{"time":0.1667,"angle":0,"curve":"stepped"},{"time":0.2333,"angle":0}],"translate":[{"time":0,"x":0,"y":0},{"time":0.1333,"x":0,"y":5.56,"curve":[0.131,0.18,0.495,0.83]},{"time":0.2333,"x":0,"y":6.96}],"scale":[{"time":0,"x":1,"y":1},{"time":0.1667,"x":1,"y":0.918,"curve":"stepped"},{"time":0.2333,"x":1,"y":0.918}]},"chicken/eye_Rb":{"rotate":[{"time":0,"angle":0,"curve":"stepped"},{"time":0.1667,"angle":0,"curve":"stepped"},{"time":0.2333,"angle":0}],"translate":[{"time":0,"x":0,"y":0},{"time":0.1333,"x":0,"y":5.56,"curve":[0.131,0.18,0.495,0.83]},{"time":0.2333,"x":0,"y":6.96}],"scale":[{"time":0,"x":1,"y":1},{"time":0.1667,"x":1,"y":0.918,"curve":"stepped"},{"time":0.2333,"x":1,"y":0.918}]},"light_L":{"rotate":[{"time":0,"angle":0,"curve":"stepped"},{"time":0.2333,"angle":0}],"translate":[{"time":0,"x":0,"y":0,"curve":"stepped"},{"time":0.2333,"x":0,"y":0}],"scale":[{"time":0,"x":1,"y":1,"curve":"stepped"},{"time":0.2333,"x":1,"y":1}]},"light_L2":{"rotate":[{"time":0,"angle":0,"curve":"stepped"},{"time":0.2333,"angle":0}],"translate":[{"time":0,"x":0,"y":0,"curve":"stepped"},{"time":0.2333,"x":0,"y":0}],"scale":[{"time":0,"x":1,"y":1,"curve":"stepped"},{"time":0.2333,"x":1,"y":1}]},"mouth":{"rotate":[{"time":0,"angle":0,"curve":"stepped"},{"time":0.2333,"angle":0}],"translate":[{"time":0,"x":0,"y":0},{"time":0.1333,"x":0,"y":2.45,"curve":[0.181,0.19,0.654,0.84]},{"time":0.2333,"x":0,"y":3.06}],"scale":[{"time":0,"x":1,"y":1,"curve":"stepped"},{"time":0.2333,"x":1,"y":1}]},"root":{"rotate":[{"time":0,"angle":0,"curve":"stepped"},{"time":0.2333,"angle":0}],"translate":[{"time":0,"x":0,"y":0,"curve":"stepped"},{"time":0.2333,"x":0,"y":0}],"scale":[{"time":0,"x":1,"y":1,"curve":"stepped"},{"time":0.2333,"x":1,"y":1}]},"chicken/top":{"rotate":[{"time":0,"angle":0,"curve":"stepped"},{"time":0.2333,"angle":0}],"translate":[{"time":0,"x":0,"y":0,"curve":"stepped"},{"time":0.2333,"x":0,"y":0}],"scale":[{"time":0,"x":1,"y":1,"curve":"stepped"},{"time":0.2333,"x":1,"y":1}]},"gold_shark/eye_L":{"rotate":[{"time":0,"angle":0,"curve":"stepped"},{"time":0.2333,"angle":0}],"translate":[{"time":0,"x":0,"y":0},{"time":0.1667,"x":0,"y":5.14,"curve":"stepped"},{"time":0.2333,"x":0,"y":5.14}],"scale":[{"time":0,"x":1,"y":1},{"time":0.1667,"x":1,"y":0.91,"curve":"stepped"},{"time":0.2333,"x":1,"y":0.91}]},"gold_shark/eye_R":{"rotate":[{"time":0,"angle":0,"curve":"stepped"},{"time":0.2333,"angle":0}],"translate":[{"time":0,"x":0,"y":0},{"time":0.1667,"x":0,"y":5.14,"curve":"stepped"},{"time":0.2333,"x":0,"y":5.14}],"scale":[{"time":0,"x":1,"y":1},{"time":0.1667,"x":1,"y":0.91,"curve":"stepped"},{"time":0.2333,"x":1,"y":0.91}]},"up":{"rotate":[{"time":0,"angle":0,"curve":"stepped"},{"time":0.2333,"angle":0}],"translate":[{"time":0,"x":0,"y":0,"curve":[0.504,0.08,0.514,0.88]},{"time":0.1333,"x":0,"y":-2.83,"curve":[0.109,0.15,0.49,0.8]},{"time":0.2333,"x":0,"y":-3.06}],"scale":[{"time":0,"x":1,"y":1.031,"curve":"stepped"},{"time":0.2333,"x":1,"y":1.031}]},"chicken/btm":{"rotate":[{"time":0,"angle":0,"curve":"stepped"},{"time":0.1667,"angle":0,"curve":"stepped"},{"time":0.2333,"angle":0}],"translate":[{"time":0,"x":0,"y":0},{"time":0.1333,"x":0,"y":4.94,"curve":[0.131,0.18,0.604,0.79]},{"time":0.2333,"x":0,"y":6.17}],"scale":[{"time":0,"x":1,"y":1,"curve":"stepped"},{"time":0.1667,"x":1,"y":1,"curve":"stepped"},{"time":0.2333,"x":1,"y":1}]}}},"up2":{"slots":{"chicken/c1":{"attachment":[{"time":0,"name":null}]},"chicken/light":{"attachment":[{"time":0,"name":null}]},"chicken/mouth1_3":{"attachment":[{"time":0,"name":"chicken/mouth1_3"}]},"eye_Lb_add":{"attachment":[{"time":0,"name":null}]},"eye_Rb_add":{"attachment":[{"time":0,"name":null}]},"light2":{"attachment":[{"time":0,"name":null}]}},"bones":{"object/head_3":{"rotate":[{"time":0,"angle":0}],"translate":[{"time":0,"x":0,"y":-3.06}],"scale":[{"time":0,"x":0.954,"y":0.988},{"time":0.2,"x":0.938,"y":0.984,"curve":[0.543,0.13,0.505,0.86]},{"time":0.6333,"x":0.972,"y":0.992,"curve":[0.548,0.14,0.909,0.83]},{"time":0.8667,"x":0.954,"y":0.988}]},"chicken/eye_Lb":{"rotate":[{"time":0,"angle":0}],"translate":[{"time":0,"x":0,"y":6.96}],"scale":[{"time":0,"x":1,"y":0.918}]},"chicken/eye_Rb":{"rotate":[{"time":0,"angle":0}],"translate":[{"time":0,"x":0,"y":6.96}],"scale":[{"time":0,"x":1,"y":0.918}]},"light_L":{"rotate":[{"time":0,"angle":0}],"translate":[{"time":0,"x":0,"y":0}],"scale":[{"time":0,"x":1,"y":1}]},"light_L2":{"rotate":[{"time":0,"angle":0}],"translate":[{"time":0,"x":0,"y":0}],"scale":[{"time":0,"x":1,"y":1}]},"mouth":{"rotate":[{"time":0,"angle":0}],"translate":[{"time":0,"x":0,"y":3.06}],"scale":[{"time":0,"x":1,"y":1},{"time":0.4333,"x":1.059,"y":1,"curve":[0.503,0.13,0.525,0.84]},{"time":0.8667,"x":1,"y":1}]},"root":{"rotate":[{"time":0,"angle":0}],"translate":[{"time":0,"x":0,"y":0}],"scale":[{"time":0,"x":1,"y":1}]},"chicken/top":{"rotate":[{"time":0,"angle":0}],"translate":[{"time":0,"x":0,"y":0}],"scale":[{"time":0,"x":1,"y":1},{"time":0.4333,"x":1,"y":0.949,"curve":[0.496,0.12,0.491,0.86]},{"time":0.8667,"x":1,"y":1}]},"gold_shark/eye_L":{"rotate":[{"time":0,"angle":0}],"translate":[{"time":0,"x":0,"y":5.14}],"scale":[{"time":0,"x":1,"y":0.91}]},"gold_shark/eye_R":{"rotate":[{"time":0,"angle":0}],"translate":[{"time":0,"x":0,"y":5.14}],"scale":[{"time":0,"x":1,"y":0.91}]},"up":{"rotate":[{"time":0,"angle":0}],"translate":[{"time":0,"x":0,"y":-3.06}],"scale":[{"time":0,"x":1,"y":1.031},{"time":0.2,"x":1,"y":1.068,"curve":[0.504,0.08,0.514,0.88]},{"time":0.6333,"x":1,"y":1,"curve":[0.504,0.08,0.909,0.86]},{"time":0.8667,"x":1,"y":1.031}]},"chicken/btm":{"rotate":[{"time":0,"angle":0}],"translate":[{"time":0,"x":0,"y":6.17}],"scale":[{"time":0,"x":1,"y":1}]}}},"up3":{"slots":{"chicken/c1":{"attachment":[{"time":0,"name":null},{"time":0.2,"name":null}]},"chicken/light":{"attachment":[{"time":0,"name":null},{"time":0.2,"name":null}]},"chicken/mouth1_3":{"attachment":[{"time":0,"name":"chicken/mouth1_3"},{"time":0.2,"name":"chicken/mouth1_3"}]},"eye_Lb_add":{"attachment":[{"time":0,"name":null},{"time":0.2,"name":null}]},"eye_Rb_add":{"attachment":[{"time":0,"name":null},{"time":0.2,"name":null}]},"light2":{"attachment":[{"time":0,"name":null},{"time":0.2,"name":null}]}},"bones":{"object/head_3":{"rotate":[{"time":0,"angle":0,"curve":"stepped"},{"time":0.2,"angle":0}],"translate":[{"time":0,"x":0,"y":-3.06,"curve":[0.25,0,0.75,1]},{"time":0.2,"x":0,"y":0}],"scale":[{"time":0,"x":0.954,"y":0.988,"curve":"stepped"},{"time":0.2,"x":0.954,"y":0.988}]},"chicken/eye_Lb":{"rotate":[{"time":0,"angle":0,"curve":"stepped"},{"time":0.2,"angle":0}],"translate":[{"time":0,"x":0,"y":6.96,"curve":[0.25,0,0.75,1]},{"time":0.2,"x":0,"y":0}],"scale":[{"time":0,"x":1,"y":0.918},{"time":0.2,"x":1,"y":1}]},"chicken/eye_Rb":{"rotate":[{"time":0,"angle":0,"curve":"stepped"},{"time":0.2,"angle":0}],"translate":[{"time":0,"x":0,"y":6.96,"curve":[0.25,0,0.75,1]},{"time":0.2,"x":0,"y":0}],"scale":[{"time":0,"x":1,"y":0.918},{"time":0.2,"x":1,"y":1}]},"light_L":{"rotate":[{"time":0,"angle":0,"curve":"stepped"},{"time":0.2,"angle":0}],"translate":[{"time":0,"x":0,"y":0,"curve":"stepped"},{"time":0.2,"x":0,"y":0}],"scale":[{"time":0,"x":1,"y":1,"curve":"stepped"},{"time":0.2,"x":1,"y":1}]},"light_L2":{"rotate":[{"time":0,"angle":0,"curve":"stepped"},{"time":0.2,"angle":0}],"translate":[{"time":0,"x":0,"y":0,"curve":"stepped"},{"time":0.2,"x":0,"y":0}],"scale":[{"time":0,"x":1,"y":1,"curve":"stepped"},{"time":0.2,"x":1,"y":1}]},"mouth":{"rotate":[{"time":0,"angle":0,"curve":"stepped"},{"time":0.2,"angle":0}],"translate":[{"time":0,"x":0,"y":3.06,"curve":[0.25,0,0.75,1]},{"time":0.2,"x":0,"y":0}],"scale":[{"time":0,"x":1,"y":1,"curve":"stepped"},{"time":0.2,"x":1,"y":1}]},"root":{"rotate":[{"time":0,"angle":0,"curve":"stepped"},{"time":0.2,"angle":0}],"translate":[{"time":0,"x":0,"y":0,"curve":"stepped"},{"time":0.2,"x":0,"y":0}],"scale":[{"time":0,"x":1,"y":1,"curve":"stepped"},{"time":0.2,"x":1,"y":1}]},"chicken/top":{"rotate":[{"time":0,"angle":0,"curve":"stepped"},{"time":0.2,"angle":0}],"translate":[{"time":0,"x":0,"y":0,"curve":"stepped"},{"time":0.2,"x":0,"y":0}],"scale":[{"time":0,"x":1,"y":1,"curve":"stepped"},{"time":0.2,"x":1,"y":1}]},"gold_shark/eye_L":{"rotate":[{"time":0,"angle":0,"curve":"stepped"},{"time":0.2,"angle":0}],"translate":[{"time":0,"x":0,"y":5.14},{"time":0.2,"x":0,"y":0}],"scale":[{"time":0,"x":1,"y":0.91},{"time":0.2,"x":1,"y":1}]},"gold_shark/eye_R":{"rotate":[{"time":0,"angle":0,"curve":"stepped"},{"time":0.2,"angle":0}],"translate":[{"time":0,"x":0,"y":5.14},{"time":0.2,"x":0,"y":0}],"scale":[{"time":0,"x":1,"y":0.91},{"time":0.2,"x":1,"y":1}]},"up":{"rotate":[{"time":0,"angle":0,"curve":"stepped"},{"time":0.2,"angle":0}],"translate":[{"time":0,"x":0,"y":-3.06,"curve":[0.25,0,0.75,1]},{"time":0.2,"x":0,"y":0}],"scale":[{"time":0,"x":1,"y":1.031,"curve":"stepped"},{"time":0.2,"x":1,"y":1.031}]},"chicken/btm":{"rotate":[{"time":0,"angle":0,"curve":"stepped"},{"time":0.2,"angle":0}],"translate":[{"time":0,"x":0,"y":6.17,"curve":[0.25,0,0.75,1]},{"time":0.2,"x":0,"y":0}],"scale":[{"time":0,"x":1,"y":1,"curve":"stepped"},{"time":0.2,"x":1,"y":1}]}}}}},[0]]],0,0,[0],[-1],[0]]