[1,["afn23o241K2bxBmXLxVThy"],0,[["sp.SkeletonData",["_name","_atlasText","textureNames","_skeletonJson","textures"],-1,3]],[[0,0,1,2,3,4,5]],[[0,"ksxz_spine","\r\nksxz_spine.png\r\nsize: 915,308\r\nformat: RGBA8888\r\nfilter: Linear,Linear\r\nrepeat: none\r\nksxz_spine/card3\r\n  rotate: true\r\n  xy: 2, 2\r\n  size: 143, 107\r\n  orig: 143, 107\r\n  offset: 0, 0\r\n  index: -1\r\nksxz_spine/chouma_r\r\n  rotate: false\r\n  xy: 819, 215\r\n  size: 91, 91\r\n  orig: 91, 91\r\n  offset: 0, 0\r\n  index: -1\r\nksxz_spine/heitao\r\n  rotate: true\r\n  xy: 2, 147\r\n  size: 159, 158\r\n  orig: 159, 158\r\n  offset: 0, 0\r\n  index: -1\r\nksxz_spine/kai\r\n  rotate: true\r\n  xy: 360, 53\r\n  size: 125, 122\r\n  orig: 125, 122\r\n  offset: 0, 0\r\n  index: -1\r\nksxz_spine/ksxz_frame\r\n  rotate: false\r\n  xy: 380, 190\r\n  size: 437, 116\r\n  orig: 437, 116\r\n  offset: 0, 0\r\n  index: -1\r\nksxz_spine/ksxz_text\r\n  rotate: false\r\n  xy: 484, 83\r\n  size: 429, 105\r\n  orig: 429, 105\r\n  offset: 0, 0\r\n  index: -1\r\nksxz_spine/light1\r\n  rotate: true\r\n  xy: 288, 180\r\n  size: 126, 90\r\n  orig: 126, 90\r\n  offset: 0, 0\r\n  index: -1\r\nksxz_spine/light2\r\n  rotate: false\r\n  xy: 484, 2\r\n  size: 371, 79\r\n  orig: 371, 79\r\n  offset: 0, 0\r\n  index: -1\r\nksxz_spine/shi\r\n  rotate: true\r\n  xy: 162, 171\r\n  size: 135, 124\r\n  orig: 135, 124\r\n  offset: 0, 0\r\n  index: -1\r\nksxz_spine/xia\r\n  rotate: true\r\n  xy: 236, 41\r\n  size: 128, 122\r\n  orig: 128, 122\r\n  offset: 0, 0\r\n  index: -1\r\nksxz_spine/zhu\r\n  rotate: true\r\n  xy: 111, 5\r\n  size: 140, 123\r\n  orig: 140, 123\r\n  offset: 0, 0\r\n  index: -1\r\n",["ksxz_spine.png"],{"skeleton":{"hash":"mcS43uLxc4VO1Cf/xI0kCkrLA/E","spine":"3.6.53","width":874,"height":232,"images":"./image/"},"bones":[{"name":"root"},{"name":"main","parent":"root"},{"name":"ksxz_spine/ksxz_frame","parent":"main","scaleX":2,"scaleY":2},{"name":"ksxz_spine/card3","parent":"ksxz_spine/ksxz_frame","x":131.5,"y":-30,"scaleX":0.001,"scaleY":0.001},{"name":"ksxz_spine/chouma_r","parent":"ksxz_spine/ksxz_frame","x":-199.5,"y":18.5,"scaleX":0.001,"scaleY":0.001},{"name":"ksxz_spine/heitao","parent":"ksxz_spine/ksxz_frame","x":143,"y":21.5,"scaleX":0.001,"scaleY":0.001},{"name":"ksxz_spine/kai","parent":"main","x":-163,"y":-0.5},{"name":"ksxz_spine/ksxz_text","parent":"ksxz_spine/ksxz_frame","y":-1},{"name":"ksxz_spine/light1","parent":"main","x":-206,"y":-25.5,"scaleX":0.001,"scaleY":0.001},{"name":"ksxz_spine/light2","parent":"main","x":13.5,"y":1,"scaleX":0.001,"scaleY":2.5},{"name":"ksxz_spine/shi","parent":"main","x":-55,"y":2},{"name":"ksxz_spine/xia","parent":"main","x":51.5,"y":-0.5},{"name":"ksxz_spine/zhu","parent":"main","x":154.5,"y":1.5},{"name":"light1_L1","parent":"main","x":-11.5,"y":12,"scaleX":0.001,"scaleY":0.001},{"name":"light1_L2","parent":"main","x":173.5,"y":43,"scaleX":0.001,"scaleY":0.001},{"name":"light1_L3","parent":"main","x":268.5,"y":-46,"scaleX":0.001,"scaleY":0.001},{"name":"light1_L4","parent":"main","x":-210.5,"y":49,"scaleX":0.001,"scaleY":0.001},{"name":"light2_L1","parent":"main","x":13.5,"y":1,"scaleX":0.001,"scaleY":3},{"name":"light2_L2","parent":"main","x":-58.5,"y":-27,"scaleX":0.001},{"name":"light2_L3","parent":"main","x":40.5,"y":35,"scaleX":0.001}],"slots":[{"name":"ksxz_spine/heitao","bone":"ksxz_spine/heitao","attachment":"ksxz_spine/heitao"},{"name":"ksxz_spine/card3","bone":"ksxz_spine/card3","attachment":"ksxz_spine/card3"},{"name":"ksxz_spine/ksxz_frame","bone":"ksxz_spine/ksxz_frame","color":"ffffff00","attachment":"ksxz_spine/ksxz_frame"},{"name":"ksxz_spine/ksxz_text","bone":"ksxz_spine/ksxz_text","color":"ffffff00","attachment":"ksxz_spine/ksxz_text"},{"name":"ksxz_spine/chouma_r","bone":"ksxz_spine/chouma_r","attachment":"ksxz_spine/chouma_r"},{"name":"ksxz_spine/kai","bone":"ksxz_spine/kai","color":"ffffff00"},{"name":"ksxz_spine/shi","bone":"ksxz_spine/shi","color":"ffffff00"},{"name":"ksxz_spine/xia","bone":"ksxz_spine/xia","color":"ffffff00"},{"name":"ksxz_spine/zhu","bone":"ksxz_spine/zhu","color":"ffffff00"},{"name":"light1_L4","bone":"light1_L4","blend":"screen"},{"name":"light1_L3","bone":"light1_L3","blend":"screen"},{"name":"light1_L2","bone":"light1_L2","blend":"screen"},{"name":"light1_L1","bone":"light1_L1","blend":"screen"},{"name":"ksxz_spine/light1","bone":"ksxz_spine/light1","blend":"screen"},{"name":"light2_L3","bone":"light2_L3","blend":"screen"},{"name":"light2_L2","bone":"light2_L2","blend":"screen"},{"name":"light2_L1","bone":"light2_L1","blend":"screen"},{"name":"ksxz_spine/light2","bone":"ksxz_spine/light2"}],"skins":{"default":{"ksxz_spine/card3":{"ksxz_spine/card3":{"x":25,"y":44,"width":143,"height":107}},"ksxz_spine/chouma_r":{"ksxz_spine/chouma_r":{"width":91,"height":91}},"ksxz_spine/heitao":{"ksxz_spine/heitao":{"x":25,"y":-26,"width":159,"height":158}},"ksxz_spine/kai":{"ksxz_spine/kai":{"width":125,"height":122}},"ksxz_spine/ksxz_frame":{"ksxz_spine/ksxz_frame":{"width":437,"height":116}},"ksxz_spine/ksxz_text":{"ksxz_spine/ksxz_text":{"width":429,"height":105}},"ksxz_spine/light1":{"ksxz_spine/light1":{"x":-12,"y":1.5,"width":126,"height":90}},"ksxz_spine/light2":{"ksxz_spine/light2":{"x":38,"y":-4,"width":371,"height":79}},"ksxz_spine/shi":{"ksxz_spine/shi":{"width":135,"height":124}},"ksxz_spine/xia":{"ksxz_spine/xia":{"width":128,"height":122}},"ksxz_spine/zhu":{"ksxz_spine/zhu":{"width":140,"height":123}},"light1_L1":{"ksxz_spine/light1":{"x":-12,"y":1.5,"width":126,"height":90}},"light1_L2":{"ksxz_spine/light1":{"x":-12,"y":1.5,"width":126,"height":90}},"light1_L3":{"ksxz_spine/light1":{"x":-12,"y":1.5,"width":126,"height":90}},"light1_L4":{"ksxz_spine/light1":{"x":-12,"y":1.5,"width":126,"height":90}},"light2_L1":{"ksxz_spine/light2":{"x":38,"y":-4,"width":371,"height":79}},"light2_L2":{"ksxz_spine/light2":{"x":38,"y":-4,"width":371,"height":79}},"light2_L3":{"ksxz_spine/light2":{"x":38,"y":-4,"width":371,"height":79}}}},"animations":{"animation":{"slots":{"ksxz_spine/card3":{"color":[{"time":0,"color":"ffffffff","curve":"stepped"},{"time":1.2667,"color":"ffffffff"},{"time":1.3667,"color":"ffffff00"}],"attachment":[{"time":0,"name":"ksxz_spine/card3"},{"time":1.3667,"name":null}]},"ksxz_spine/chouma_r":{"color":[{"time":0,"color":"ffffffff","curve":"stepped"},{"time":1.2667,"color":"ffffffff"},{"time":1.3667,"color":"ffffff00"}],"attachment":[{"time":0,"name":"ksxz_spine/chouma_r"},{"time":1.3667,"name":null}]},"ksxz_spine/heitao":{"color":[{"time":0,"color":"ffffffff","curve":"stepped"},{"time":1.2667,"color":"ffffffff"},{"time":1.3667,"color":"ffffff00"}],"attachment":[{"time":0,"name":"ksxz_spine/heitao"},{"time":1.3667,"name":null}]},"ksxz_spine/kai":{"color":[{"time":0,"color":"ffffff00","curve":"stepped"},{"time":0.5,"color":"ffffff00"},{"time":0.5667,"color":"ffffffff","curve":"stepped"},{"time":0.6333,"color":"ffffffff"},{"time":0.7,"color":"ffffff00"}],"attachment":[{"time":0,"name":"ksxz_spine/kai"},{"time":0.5,"name":"ksxz_spine/kai"},{"time":0.7,"name":null}]},"ksxz_spine/ksxz_frame":{"color":[{"time":0,"color":"ffffff00","curve":"stepped"},{"time":0.1667,"color":"ffffff00"},{"time":0.2667,"color":"ffffffff","curve":"stepped"},{"time":1.2667,"color":"ffffffff"},{"time":1.3667,"color":"ffffff00"}],"attachment":[{"time":0,"name":"ksxz_spine/ksxz_frame"},{"time":1.3667,"name":null}]},"ksxz_spine/ksxz_text":{"color":[{"time":0,"color":"ffffff00","curve":"stepped"},{"time":0.1667,"color":"ffffff00"},{"time":0.5667,"color":"ffffffff","curve":"stepped"},{"time":1.2667,"color":"ffffffff"},{"time":1.3667,"color":"ffffff00"}],"attachment":[{"time":0,"name":"ksxz_spine/ksxz_text"},{"time":1.3667,"name":null}]},"ksxz_spine/light1":{"attachment":[{"time":0,"name":"ksxz_spine/light1"},{"time":0.4667,"name":"ksxz_spine/light1"},{"time":0.9,"name":null}]},"ksxz_spine/light2":{"attachment":[{"time":0,"name":"ksxz_spine/light2"},{"time":1.2,"name":"ksxz_spine/light2"},{"time":1.3667,"name":null}]},"ksxz_spine/shi":{"color":[{"time":0,"color":"ffffff00","curve":"stepped"},{"time":0.5667,"color":"ffffff00"},{"time":0.6333,"color":"ffffffff","curve":"stepped"},{"time":0.7,"color":"ffffffff"},{"time":0.7667,"color":"ffffff00"}],"attachment":[{"time":0,"name":"ksxz_spine/shi"},{"time":0.5667,"name":"ksxz_spine/shi"},{"time":0.7667,"name":null}]},"ksxz_spine/xia":{"color":[{"time":0,"color":"ffffff00","curve":"stepped"},{"time":0.6333,"color":"ffffff00"},{"time":0.7,"color":"ffffffff","curve":"stepped"},{"time":0.7667,"color":"ffffffff"},{"time":0.8333,"color":"ffffff00"}],"attachment":[{"time":0,"name":"ksxz_spine/xia"},{"time":0.6333,"name":"ksxz_spine/xia"},{"time":0.8333,"name":null}]},"ksxz_spine/zhu":{"color":[{"time":0,"color":"ffffff00","curve":"stepped"},{"time":0.7,"color":"ffffff00"},{"time":0.7667,"color":"ffffffff","curve":"stepped"},{"time":0.8333,"color":"ffffffff"},{"time":0.9,"color":"ffffff00"}],"attachment":[{"time":0,"name":"ksxz_spine/zhu"},{"time":0.7,"name":"ksxz_spine/zhu"},{"time":0.9,"name":null}]},"light1_L1":{"attachment":[{"time":0,"name":"ksxz_spine/light1"},{"time":0.5333,"name":"ksxz_spine/light1"},{"time":0.9667,"name":null}]},"light1_L2":{"attachment":[{"time":0,"name":"ksxz_spine/light1"},{"time":0.6,"name":"ksxz_spine/light1"},{"time":1.0333,"name":null}]},"light1_L3":{"attachment":[{"time":0,"name":"ksxz_spine/light1"},{"time":0.6667,"name":"ksxz_spine/light1"},{"time":1.1,"name":null}]},"light1_L4":{"attachment":[{"time":0,"name":"ksxz_spine/light1"},{"time":0.7333,"name":"ksxz_spine/light1"},{"time":1.1667,"name":null}]},"light2_L1":{"attachment":[{"time":0,"name":"ksxz_spine/light2"},{"time":0.1667,"name":"ksxz_spine/light2"},{"time":0.3667,"name":null}]},"light2_L2":{"attachment":[{"time":0,"name":"ksxz_spine/light2"},{"time":0.5,"name":"ksxz_spine/light2"},{"time":0.8667,"name":null}]},"light2_L3":{"attachment":[{"time":0,"name":"ksxz_spine/light2"},{"time":0.6333,"name":"ksxz_spine/light2"},{"time":1,"name":null}]}},"bones":{"ksxz_spine/card3":{"translate":[{"time":0,"x":0,"y":0,"curve":"stepped"},{"time":0.4667,"x":0,"y":0},{"time":0.5667,"x":33.43,"y":40.91},{"time":0.6667,"x":30,"y":40}],"scale":[{"time":0,"x":0,"y":0,"curve":"stepped"},{"time":0.4667,"x":0,"y":0},{"time":0.5667,"x":1200,"y":1200},{"time":0.6333,"x":900,"y":900},{"time":0.7,"x":1000,"y":1000}]},"ksxz_spine/chouma_r":{"translate":[{"time":0,"x":0,"y":0,"curve":"stepped"},{"time":0.3,"x":0,"y":0},{"time":0.4,"x":-44.14,"y":51.6},{"time":0.4667,"x":-32,"y":39}],"scale":[{"time":0,"x":0,"y":0,"curve":"stepped"},{"time":0.3,"x":0,"y":0},{"time":0.4,"x":1200,"y":1200},{"time":0.4667,"x":900,"y":900},{"time":0.5333,"x":1000,"y":1000}]},"ksxz_spine/heitao":{"translate":[{"time":0,"x":0,"y":0,"curve":"stepped"},{"time":0.3667,"x":0,"y":0},{"time":0.5333,"x":42.43,"y":-43.43},{"time":0.6,"x":30,"y":-30}],"scale":[{"time":0,"x":0,"y":0,"curve":"stepped"},{"time":0.3667,"x":0,"y":0},{"time":0.4667,"x":1200,"y":1200},{"time":0.5333,"x":900,"y":900},{"time":0.6,"x":1000,"y":1000}]},"ksxz_spine/ksxz_frame":{"scale":[{"time":0,"x":1,"y":1,"curve":"stepped"},{"time":0.1667,"x":1,"y":1},{"time":0.2667,"x":0.4,"y":0.4},{"time":0.3667,"x":0.525,"y":0.525},{"time":0.4333,"x":0.5,"y":0.5,"curve":"stepped"},{"time":1.2667,"x":0.5,"y":0.5},{"time":1.3,"x":0.6,"y":0.6},{"time":1.3667,"x":0.25,"y":0.25}]},"ksxz_spine/light1":{"rotate":[{"time":0,"angle":0,"curve":"stepped"},{"time":0.4667,"angle":0},{"time":0.9,"angle":-90}],"scale":[{"time":0,"x":0,"y":0,"curve":"stepped"},{"time":0.4667,"x":0,"y":0},{"time":0.6667,"x":1000,"y":1000},{"time":0.9,"x":0,"y":0}]},"ksxz_spine/light2":{"scale":[{"time":0,"x":0,"y":1,"curve":"stepped"},{"time":1.2,"x":0,"y":1},{"time":1.3667,"x":3000,"y":0}]},"light1_L1":{"rotate":[{"time":0,"angle":0,"curve":"stepped"},{"time":0.5333,"angle":0},{"time":0.9667,"angle":-90}],"scale":[{"time":0,"x":0,"y":0,"curve":"stepped"},{"time":0.5333,"x":0,"y":0},{"time":0.7333,"x":1000,"y":1000},{"time":0.9667,"x":0,"y":0}]},"light1_L2":{"rotate":[{"time":0,"angle":0,"curve":"stepped"},{"time":0.6,"angle":0},{"time":1.0333,"angle":-90}],"scale":[{"time":0,"x":0,"y":0,"curve":"stepped"},{"time":0.6,"x":0,"y":0},{"time":0.8,"x":1000,"y":1000},{"time":1.0333,"x":0,"y":0}]},"light1_L3":{"rotate":[{"time":0,"angle":0,"curve":"stepped"},{"time":0.6667,"angle":0},{"time":1.1,"angle":-90}],"scale":[{"time":0,"x":0,"y":0,"curve":"stepped"},{"time":0.6667,"x":0,"y":0},{"time":0.8667,"x":1000,"y":1000},{"time":1.1,"x":0,"y":0}]},"light1_L4":{"rotate":[{"time":0,"angle":0,"curve":"stepped"},{"time":0.7333,"angle":0},{"time":1.1667,"angle":-90}],"scale":[{"time":0,"x":0,"y":0,"curve":"stepped"},{"time":0.7333,"x":0,"y":0},{"time":0.9333,"x":1000,"y":1000},{"time":1.1667,"x":0,"y":0}]},"light2_L1":{"scale":[{"time":0,"x":0,"y":1,"curve":"stepped"},{"time":0.1667,"x":0,"y":1},{"time":0.3667,"x":3000,"y":0}]},"light2_L2":{"scale":[{"time":0,"x":0,"y":1,"curve":"stepped"},{"time":0.5,"x":0,"y":1},{"time":0.8667,"x":2000,"y":0}]},"light2_L3":{"scale":[{"time":0,"x":0,"y":1,"curve":"stepped"},{"time":0.6333,"x":0,"y":1},{"time":1,"x":2000,"y":0}]},"main":{"translate":[{"time":0,"x":0,"y":0}]}}}}},[0]]],0,0,[0],[-1],[0]]