{"paths":{"0":["font/sz_pdk3",1],"1":["effect/325_tbnn_caijinchi/325_tbnn_caijinchi",1],"2":["font/sz-tbnn-02",1],"3":["font/numberhx",1],"4":["sound/sound-tie",8],"5":["sound/M_OX_3",8],"6":["sound/M_OX_1",8],"7":["gui/gui-bg-game",1],"8":["effect/tongbiniuniu4_kaishi/tongbiniuniu4_kaishi",1],"9":["font/numb",1],"10":["sound/F_OX_6",8],"11":["sound/F_OX_5",8],"12":["sound/M_OX_5",8],"13":["effect/tongbiniuniu4_saoguang/325_tbnn_cjcsaoguang",2],"14":["sound/M_OX_0",8],"15":["effect/325_qiangzhuangniuniu_dashichang/325_qiangzhuangniuniu_dashichang",1],"16":["sound/M_OX_9",8],"17":["gui/gui-rule-bg",1],"18":["sound/fly_gold",8],"19":["font/sz-tbnn-05",1],"20":["sound/audio_reminded",8],"21":["sound/sound-ready",8],"22":["sound/F_OX_3",8],"23":["sound/start",8],"24":["effect/325_qiangzhuangniuniu_dashichang/325_qiangzhuangniuniu_dashichang",2],"25":["sound/M_OX_4",8],"26":["effect/325_tbnn_caijinchi/325_tbnn_caijinchi",2],"27":["font/jb_num",1],"28":["gui/tbnn_card",1],"29":["sound/F_OX_1",8],"30":["gui/gui-room-bg",1],"31":["font/txt_cc",1],"32":["font/numsilver",1],"33":["font/txt_gold",1],"34":["sound/M_OX_6",8],"35":["sound/M_OX_8",8],"36":["sound/win",8],"37":["sound/F_OX_10",8],"38":["effect/tongbiniuniu4_kaishi/tongbiniuniu4_kaishi",2],"39":["effect/tongbiniuniu4_jiesuan/tongbiniuniu4_jiesuan",1],"40":["effect/tongbiniuniu4_saoguang/325_tbnn_cjcsaoguang",1],"41":["gui/gui-roomChoose",1],"42":["sound/F_OX_9",8],"43":["sound/M_OX_2",8],"44":["effect/star_1",4],"45":["sound/Ox_11",8],"46":["gui/325_tongbiniuniu_huohua",4],"47":["sound/fail",8],"48":["font/tbnn_font_1",1],"49":["effect/tongbiniuniu4_dengdaixiaju/tongbiniuniu4_dengdaixiaju",1],"50":["effect/tongbiniuniu4_jiesuan/tongbiniuniu4_jiesuan",2],"51":["effect/tongbiniuniu4_dengdaixiaju/tongbiniuniu4_dengdaixiaju",2],"52":["sound/bkmusic2",8],"53":["font/txt_jlgold",1],"54":["gui/gui-bank",1],"55":["sound/F_OX_2",8],"56":["sound/F_OX_8",8],"57":["sound/M_OX_10",8],"58":["sound/F_OX_7",8],"59":["sound/sendcard",8],"60":["sound/M_OX_7",8],"61":["font/tbnn_number_blue",1],"62":["sound/OX_12",8],"63":["gui/gui-rule-content",1],"64":["gui/gui-bank-bg",1],"65":["font/tbnn_rc_num",1],"66":["effect/tongbiniuniu4_saoguang/325_tbnn_cjcsaoguang",3],"67":["font/jiangjin",1],"68":["sound/F_OX_4",8],"69":["font/sz_pdk4",1],"70":["gui/tbnn_plist",1],"71":["sound/F_OX_0",8],"72":["font/txt_gold",5],"73":["effect/tongbiniuniu4_kaishi/tongbiniuniu4_kaishi",0,1],"74":["gui/tbnn_plist",6],"75":["effect/325_tbnn_caijinchi/325_tbnn_caijinchi",3],"76":["effect/325_tbnn_caijinchi/325_tbnn_caijinchi",0,1],"77":["effect/325_qiangzhuangniuniu_dashichang/325_qiangzhuangniuniu_dashichang",0,1],"78":["prefab/Room_Load",7],"79":["font/numberhx",0,1],"80":["gui/gui-rule-bg",0,1],"81":["font/txt_jlgold",0,1],"82":["font/sz-tbnn-05",5],"83":["font/txt_gold",0,1],"84":["effect/tongbiniuniu4_jiesuan/tongbiniuniu4_jiesuan",0,1],"85":["font/tbnn_font_1",0,1],"86":["font/txt_cc",5],"88":["font/numberhx",5],"89":["font/sz-tbnn-02",0,1],"90":["prefab/Rule",7],"92":["font/numsilver",0,1],"93":["font/txt_jlgold",5],"94":["font/tbnn_number_blue",0,1],"95":["font/sz_pdk3",5],"96":["font/numb",0,1],"97":["prefab/TBNNMain",7],"98":["font/tbnn_rc_num",0,1],"100":["font/txt_cc",0,1],"101":["gui/gui-roomChoose",6],"102":["gui/gui-bg-game",0,1],"103":["effect/tongbiniuniu4_kaishi/tongbiniuniu4_kaishi",3],"106":["font/sz_pdk4",0,1],"107":["gui/gui-room-bg",0,1],"108":["prefab/Table",7],"109":["gui/tbnn_card",6],"110":["font/numb",5],"111":["effect/325_qiangzhuangniuniu_dashichang/325_qiangzhuangniuniu_dashichang",3],"113":["font/sz_pdk3",0,1],"114":["effect/tongbiniuniu4_jiesuan/tongbiniuniu4_jiesuan",3],"115":["gui/gui-rule-content",0,1],"116":["prefab/Bank",7],"117":["gui/gui-bank",6],"118":["prefab/TBNNGame",7],"119":["effect/tongbiniuniu4_dengdaixiaju/tongbiniuniu4_dengdaixiaju",0,1],"120":["font/sz-tbnn-02",5],"121":["font/jb_num",0,1],"122":["font/jiangjin",0,1],"124":["font/jb_num",5],"126":["font/sz_pdk4",5],"127":["effect/tongbiniuniu4_saoguang/325_tbnn_cjcsaoguang",3],"128":["effect/tongbiniuniu4_saoguang/325_tbnn_cjcsaoguang",0,1],"129":["font/sz-tbnn-05",0,1],"130":["effect/tongbiniuniu4_dengdaixiaju/tongbiniuniu4_dengdaixiaju",3],"131":["gui/gui-bank-bg",0,1],"133":["font/tbnn_rc_num",5],"134":["font/jiangjin",5],"135":["font/numsilver",5]},"types":["cc.SpriteFrame","cc.Texture2D","cc.Asset","sp.SkeletonData","cc.ParticleAsset","cc.BitmapFont","cc.SpriteAtlas","cc.Prefab","cc.AudioClip"],"uuids":["00OZ2URIJFkZ9V6rtw21K9","01w7Vc0ZpNAa7Z7yUBjTxw","04vT24Pk9IdpQvxfq/o0Mq","0brI2xAfdK+qn5hpnAVjAV","0equ5hZPdCaqnQbH/O8cyH","14yi9bIyxPpauXFz6ONFIT","148SHdpiFFo6YLbKf/c32o","1cwZYgNUJIVLuxOEIy6Gh+","1d6bO9NdhCEb7GyXfNKqlz","2bpwufF5hMI5y3BsUPXkfp","34otdckx5JZaq/oBJidsDb","36OzJq2stMyb7X4MrW1ikU","36gl7fA9BDFb3kxkOSroh9","38YUEYeT5EQ6/2HD8txsHV","3aT8/InkdHAqll0VEsMRHO","3c6giCKAFFU5uq/nwGJSxn","3dYa7O7ipJRLBFN9AlyIAq","3erBz3W+tIRoT4TXyFfQ/g","40T16QqkNMvKoWU3PMCMrH","45p1Vh6ohP1qJjWZ2+UCaa","46x7t4PuxFqZ9rKSbWp++k","4cj5ODxIVLj7mH6W0eec98","50NUPXevJI6pLXI0jwZCEa","5akyT0ETJH86KvkwEolkZV","5bgZg7AaVHlIgWqVRuWwH+","60wS+n0SlGLaRHMuzkc/9m","61bDjx+3hPEY6inBjwd5yE","62/lHQXVlKWLDhebBfRE5V","6fwIaWH5FCCL15RHMIN8Dd","72E8YW0wFHFbqf9BvF6+N8","74wCIMHEtGCJZZhmUtWarE","76EOVPeKNNgoXk6IBr3CuZ","76kfICto1ASY2fIQ/fROBi","76ltKMkYRD45AkOp9HaqpX","78FRiE2hxK+ZhsW4cqCJgt","7cY65LoHVJaZjlqmtbLlPI","7f8y5SYUhDdbHrkFm90M1X","86BjvY/XdNwJaDtne+3314","87um1X8EBGGqIJTjoYbJqv","8bUV9rYHJA37C92fMOTkzM","8efzragORMy652OJqQKUGb","8fUSpwQllHp49n56hAlQcE","93f085Pi5DzKWyxfV9DDXe","952w4fupxNuqRFmKTO/dvk","97Paw/5mhEa6PI2IpqOjlz","9aepkkV0dE5rPJja6O10Ib","a9A9NsaQVJSalDhHcgrPNa","aa8D6cVZlJ65aAgyk1gnn1","aeVe7tXlVB4I5enkiHYfg1","afqr1V+XhKKoSUGxFYrZUa","b3IbJ9gqFAiq7oAWBGLy2y","b6kEdmcFNLiYGTPIylwcUh","b6z6IJ+V5NbbWy86dmEhS3","b7wOwX1KVIv7xjZvGP3LA7","bb1OY+85ZI5pDLkkOAJqAT","c15H7ivI9EeqhKtnisnt0K","c4ZmJY+sVHEZNciq6RfAG0","c6wFmlYJNDdZVlxYz2yxjY","cfGM0lh3FEA5F72Benv+p+","d0EfLzhaBAL5fTSjUQuTZc","d0GSNBPaBBm5Cd42Tpkzb8","d0x4FvyeZGn7rQkHQKH4wF","d8bRtekSlEQKhAUyXnyeqo","dctDsrG91PSI/ZAAjp/zqZ","dedZ9kMTtDG47m9m/BiTqc","eaKFF6MXdCXZsUcPiBfZny","f01xJitKRC8KVEw1BqFOQz","f44uflYe9MhaPtpS1zxUSV","f5v3b3sVFJ7bwmn3j2HCOR","f8ppTuOxhBtqHA0rz53ffg","fax9f61MxGqrZH/on5sBzj","fdmMWHhkNPNLWv7E12sgUe","05k/UbTM5LmKoHLxAoYm+c","08cldkpTdAApNIjDZRgJZA","15PoRstOtE66cV892buIiN","18uF/r6SZMp73jaCzL3tdW","1aq/f1vZlIM6L42HeqvhJO","1cmOotSoFMMJQiAk8xPd9j","25zvMMkl5C/b+JOB6TXeDs","2bEztdz71FPYCMTEx+XC4k","2cuYBuQX5Db5/DMewEHV8Q","358RURZdpHDpHiEdC8g+TT","3bCnQ97S1HtaPS3YxYMp1x","3bEfOoMWBMiqbTR3Rx/Hxi","3dEp3YK9RKwI9ZJJvLO2Br","3fK5mRgTBAEb06Zu/f6CK3","3flZTae4NJc5buymhqn9Or","410b8B9Y1DWp9fngm8XEvR","42bcVahShBdKQbzQ49pFkB","49Xw4HC6BHhKNBfy6zmehy","4bBqUiX9BFUJZFL0VwfcuL","4bXT895eNA3J3C5uLceRZp","591X8kw3pDNqrj16fDVmDm","5a3lfTAklAXL89taCf74YB","5d/qrQqt9HHojCdm75zuZd","5fbY0b9FFJn6cjrGSq7YiJ","6054mWaphCkr9jfXI08bpu","63ERBgjWxAuqSGKcBVKdre","728BOjuy5J1LfOmg+a8BHU","75Wmyj471IcrrTDraK1G2n","77Dy/pvnhB34fhycmczh8t","84uIrOnAJF8qjNJ7ya2i+k","85H7++HG9IJpFbJ8mg/iQT","87q79dCVxEJYOKUoo//mAA","8f66lcPklHr7qMEsIVbdtK","92ukP/iMxNOq3l/R/3SXoS","9cve6yithJD6/QsggiuYJu","9dlou7IVFG/oGmF/LzIMQb","a1P8ffzXBG95ErQ+b0eE7l","a1YsHWIf1FbpLYXHz9btD2","acqvk/6hVHobD/0Irw+Dvv","aekWMsWR9JKKUJ9dVvbRI6","ae6ZCBn8JEEr1SSXThC5hS","b5tYA7z2hItLsnBjMbAIQN","b6YSOksmxHnqSpyPdfIjEr","b6mu5BoLZAOZ/9cM7wARW2","c0Kzh7hFJAwqe0UmEOLOtl","c9DI9zErlHv7Narc8BIgHL","ca3blG/5lN2Iuq1WKCm6Dg","cbFI5Kcb5E8a3Dxtb2NiME","ccYTHq9OdBJL2EgN7P8auB","ccn0u+rctG0ZN0jbJtl/pR","cdYb4nrh5POpw5B3A/NsJT","d0qC05vt5GxLaYyB/w3t//","d28BGiowhDi4lpaZtuwFzK","d3ZLCXESRL54w4CUWunB+5","d8L/+ZBupBRKqwPh0HOI0s","e0hhleAydCfq1Px1HX1Nc2","e0qgNeoEhFyroL2NmIhSBC","e1iJeuve5BlquEi6w2S8Sg","e2aj7uCvhL7pUzseof3KGX","e9twN/x7ZK8LOIrcn+bCrE","edJ0ZrjCpP85rRyaxbet8G","efoSpesqhDPp+Ne8ze7NPo","f1gwZEOkVNHLMJ8YwEbs3H","f7RuyiOAJHL5pyXCiOJALV","00KcW7rhZMvaiOyGr1fICC","01POkbzZ1Ft7TRtHGFyGhS","01ruuFwEdMO6DtjNeX5hvn","06Dccu4LBKW5VlBqopLTzS","07/XJe91RPD618Mu1Edg9N","0816vjXsBJX5iyrgonf2D1","09vFLfJZFJT4ewLVEr/gF4","0apXNaRc1Kb7ZcbJFpBcIi","0cjsQc+AxMUaDgsjQCzcld","0cnJMQyNNGCaBH6RPxNAzM","0eJ1flQARNfbYAKLVuO22/","0fsf61VFhED6us8URiJJQS","0f5oYcSKRNu6clA+tR4Wt0","11Di+XycpHqZIOxuNnDGE+","12DFXd6klHkrjALueYIOWO","13FE9BKjhN1a8mGfDlymFC","13nMWCZOROzpv+VS3FFifE","14JbZCjLJEGLLt3/0ISi6h","14cmwctn1JnYrDS1AZN4fw","15AtMh0axDvYVOTYhU5Git","16FAT6QfZKGrGILY9zDeHR","18WflijVVI6LhPcfLVpVR1","1cZfAeVPVGYpfR6bvQ1erB","20wsj0Lm9OBbdTb00iBSpB","212/5gM5RDtamdH9Lz4ZSI","22dYhk5pRABrbdZGmH61r/","25Lw3SaA5KP7DX0EHRJsuq","25dyCfGORONZ4FI44tIMQX","25iv/3+X5MDq4WAmNkZuJZ","25vQdq6tNGgofxWeYlEaaR","26vP4j16xF6qGeFZ2RtMLe","28j1mQM3dE2LroPrkutWx1","29FYIk+N1GYaeWH/q1NxQO","2csiBvGcJAkKHS21k11Nf8","2ehBTqvaFKvohGfC8cYqei","2fL0khHwNP4Zi6Qqw6kafj","2fRGfRcJpDvYysIuDgvIB9","2feMEU3EdCrL+pugK3haEu","2f0sI/QeRJUb1ioVI8PYm3","2f8L/AiXBAa5AQE8xsan+S","33xOn9gvhO8o4ihw26mzhi","35WGzU06VP+6Rlbmftq2B1","36CohRtOxGY4HnJLztXu4g","39EGiaFadNj7PGURl8XWHa","399LDP3+9N5Zc9dJ6Ey0Sx","39+JclpPFAtp6c/GIHUGFq","3ae7efMv1CLq2ilvUY/tQi","3awOvYoaROr52upECtlJbb","3a2Arf+GFL+YYAXNTjQeRH","3b/ncwrQhNHaZ9FAZNg1p9","3cVt+M5VxCJZTuRFJPznzY","3ffUlzDE9PRqazwQLzR+aq","40W7KoyGhC4rQUhTP1e9iS","43ETW74QZNKbJHx64jSVL/","43SxRrzdNFtqR4KQCwFfGY","47LfXTNedBhJ5sf0G+5l7j","4afsiZRhNA7ZtYl/wsMfkW","4cawsmHuhJeo34axnIwWTi","4cx9LUJEZMfqjJtAJ3Ae6X","50HKOQoOZDyJW2jDZusxkf","52K75FZ/JMereU4MR3YDNa","52ukOlwtBI3IwjwqmvWjVb","56rSXVCIlA0KgYW4Nz2Kq3","576Svz7QFKuZh5FxFyxhhq","59XWRjj79Pn7jaBZhXRy8j","60gfqfA2pMC7vget9bY53j","64IAj1NQNPmrr05NdmjEBp","67mgvpFqVGI5h5YAljiaO3","67rSZUw1BHarvlBaWeCiE9","6bUfOznctKh5I0XMe/2X2v","6f1yR+CgdFIKMrkNY8eqo9","72lrWeUGlBvbllF8xMLNgP","731vDCmatKPLTc8zFdcCuM","74pVnF3VZIIKxXeYUCqlBK","74v8S60RZICY4Qo28RB2q5","7avR1VrtdMQJM55iGPm1op","7a/QZLET9IDreTiBfRn2PD","7c7feh0ihEN52yTBE5cI6v","7ehv03MLhPXJVwQdcDvthW","7e9vLRxiNHY6eTho/2A3xM","7fWhA+enpMsaUee3a84Ufv","7f75ceH3lEv43cdWGe71aC","816akcogZKObEYHJ5l78Nz","84tmV8VGtLrKtSJpNWkJih","86AtybouxCbKO58yX1GgpO","87u40VTA5PKoYMPSaPLX1R","88Z14eAjNJU7X5HxvxRel0","8984OTQxVHtYIqs+XYOn4e","8aMU1ThipE6bNWm8rXsUGs","8ba4fh3xtMMpXKRrmo64R1","8cs/EvDN9HM6SyzdJecYk8","8c+T+xvdpLUYo+1SwWpCt/","8dX4G8rjRImZYyq+W0ZtuX","8eXNMOG7tAS7KkuiivJzrr","8fE/C4watIJJCuILY+76L9","90x2qkRzZOJa3zq+8jlFcR","91dByo5VhC5KBoK/efkebR","92pQKNpjBNZ5Ow1RDoipN7","97SdlLc31JWpoafz2c+9J/","98BaQ3CABHv7qF55DDHf7H","9aUeoGzBhFFKiKpZHGCgKu","9bKY/b8o9LSIBBz5tyjugV","9bqnjb7pRJi7zk5xCUbwLo","9cvd8rFDhPO4yINFLgvygD","9dcgt1EXBH+YIZxIYE1I9w","9f5fXHPJJDcYEhRhXbgCGk","a18ncI+HxHbLpF5Py6BV1L","a2MjXRFdtLlYQ5ouAFv/+R","a2zcaox8RNtZCfg1Qqt3LM","a31mHIheVApbDl4nBfqxgm","a4uf1Pt0hLFIutvuz7iMHh","a7VeRdSaFEZbS2B4XMJsJP","a79l0AzmlPxZ1U1DUxgmNr","a8lTm11FVDfpJ0pjth9o2J","abwArGPENFMr8k7dcGd+dc","advQToGTpAsoxE7Wc26e1F","afbY5jx5pC+KM78CNqO/Ko","afkJwUBPlDcImvZSOSSEW2","b16fZp289Jno6PyCfNvm3c","b2k2WEkglH97nmJTJKxA52","b7L1o69EpIaJVnJJR1eDBr","baGUb/UJVHxYGZvNn3JEh1","bbX5ySxXZKyrpSZoK8a9La","bbwt+MufdBiI3CumQiRe07","bb3D05vi5MvoW9X5X1jRTv","bcT92wNElLYphyx+YEq++z","bdXKhfi+lCFYqluMBCmDi+","bfvwbc2cxJlpozyNBV4NMW","c3y0lB+S9PP7BsT0UqDkwE","c4a/WnCDNIz49BGO7di1VZ","c61pboDOdL1Lkq/L5xjjM+","c7dagTPZNF1qLgAPhqxanb","c85g7RDKdFkaf+DBbUO5Dt","caYqVeQ8dBDIJedJvrjNpk","cbpO0KwQ1PLIftxHfp6enL","ccNBnuZyBPu6QxP6lAf8Qs","d1WLL6EllBFbCPfA4YAn6+","d2G8TpuQJHIKOwygJzbBEL","d3C+KLpuFDqYy1y3GyWagu","d6zs7KaRRH86oC/feqjBVQ","d7jsWyxtZI8LUzNQ8G+XYj","d7n7TQIptJFYHa4oMo4094","db7bxPb/1L+6WsfZqESF+R","dfqzqxLolF44/3tRmAw3dh","dftZB0p0NOVafEGjaOb+pC","e0oIhtoi5L147X9wk96mYn","e05IdPkR5Gmaw3xYLlgn4l","e1iJAkJshLlYbRkd5Vkyt1","e7q6FL+VZEgLJUjVeDLic/","e78bH4YxRM5ptTgsBoWZhL","e80nMEYExCAJNsCA5jMEOl","eaRVuGNPhI8rw3oLW40YY5","ecpdLyjvZBwrvm+cedCcQy","efA93jGVZEtYa4/p7Jm83B","f1WEq54LtNF6mbYYjg06Xn","f2ltsw4MVCPaUzjahLgfod","f30n2qMLlJ+JYphfLhbN7u","f4UHhXGuBO/pPzAxeopMr6","f6AW/ZypVKwJ2uH6UuSOrB","f8mPQtufZIi7n5hNYbzU2a","fcsy6ip9xFgapReWIACnPi","fdIr+h7+hJYbKKumapOwAe","fethLshWJF+4sebLySmRC3"],"scenes":{},"redirect":[140,0,157,0,162,0,168,0,169,0,170,0,180,1,182,2,187,0,196,0,204,0,210,0,212,2,223,0,224,0,234,0,240,0,243,0,265,0,280,0,284,0,288,2],"deps":["resources","main","internal"],"packs":{"015a413c1":[81,93],"01790b9ae":[80,90,115],"0247dee71":[78,219,227,258,287,290],"02e87bd2b":[0,1,2,3,7,8,9,15,17,87,19,27,28,30,99,31,32,33,39,40,41,104,105,48,112,49,53,54,123,61,125,63,64,65,132,67,69,70],"03e8a91eb":[141,143,159,166,171,184,189,215,228,237,252,254,259,264,278,282,285,289],"050a3d993":[121,124],"057aea08d":[151,117],"05c08ac69":[122,134],"063aec021":[98,133],"067f55528":[197,256],"06b5a331d":[136,137,139,154,155,172,173,175,177,179,181,188,199,200,203,205,206,209,221,230,231,233,238,109,244,251,263,268,269,270,271,274,276,292,295,297,298],"0755a9a9a":[92,135],"0784408a3":[147,183,185,195,211,218,241,267,281,296],"07e03d100":[138,142,152,216,101,273],"080b0bbed":[95,113],"08112d9fb":[106,126],"0816a96bf":[116,131],"08e89e13f":[89,120],"0b1179963":[145,146,148,149,150,153,74,156,158,160,161,164,167,176,178,186,190,193,194,198,201,202,207,214,217,220,222,225,226,229,235,236,242,245,247,248,249,253,255,257,260,261,266,277,279,283,291,293],"0b2bca7cb":[144,191,91,102,44,239,262,118,272],"0b3224d76":[163,165,174,192,208,213,246,250,275,294],"0b717a156":[96,110],"0bb796efb":[82,129],"0c26d6164":[79,88],"0d7091380":[72,83],"0ec0391b6":[232,286],"0ee271cb6":[86,100]},"name":"TBNN","importBase":"import","nativeBase":"native","debug":false,"isZip":false,"encrypted":false,"versions":{"import":["015a413c1","6e4a3","01790b9ae","c02f7","0247dee71","f7955","02e87bd2b","5b718","03e8a91eb","48795","050a3d993","89e37","057aea08d","dd36d","05c08ac69","95791","063aec021","83ebd","067f55528","fa8d5","06b5a331d","0bbf5","0755a9a9a","2bb5d","0784408a3","383b6","07e03d100","29770","080b0bbed","ff39d","08112d9fb","13eb6","0816a96bf","645bf",73,"10f98","08e89e13f","b3581","0b1179963","533cc","0b2bca7cb","03f15","0b3224d76","426ab","0b717a156","377ca","0bb796efb","e2f0d","0c26d6164","fd311","0d7091380","34018",4,"60263","0ec0391b6","b9669","0ee271cb6","48dce",5,"e0203",6,"1203f",75,"52b08",76,"26d5b",77,"bb71d",10,"859ca",11,"b0bfd",12,"66411",13,"ab124",14,"6a2a7",84,"fa435",16,"ce0f6",85,"9305c",18,"ed5c2",20,"490fd",21,"1dc93",22,"eb4e7",23,"63316",24,"19b3a",94,"dfc4d",25,"bd935",26,"9a38d",97,"fe2ac",29,"ef397",34,"23006",35,"96d9b",36,"f5916",37,"bf374",103,"3e5e6",38,"099d2",42,"33aae",43,"41e67",45,"375e9",107,"fc5d9",108,"65759",46,"fc438",47,"0f6d1",111,"059ec",50,"a22ce",114,"bde31",51,"b24af",52,"2b653",55,"8a555",56,"0c473",57,"e1680",119,"dc951",58,"3d9eb",59,"22279",60,"08600",62,"36738",127,"a588c",128,"2602f",130,"58065",66,"dacb6",68,"8ca7f",71,"53e0a"],"native":[0,"cc6ec",1,"fd160",2,"5aa98",3,"ed0ef",4,"a57d0",5,"73db7",6,"02514",7,"e29d8",8,"64143",9,"72a6a",10,"03595",11,"d4ae1",12,"6a71c",13,"d82e5",14,"17a1f",15,"bba44",16,"1af8b",17,"84577",18,"24002",87,"baebe",19,"309ed",20,"5996d",91,"8b331",21,"7b85b",22,"4ab41",23,"8a68b",24,"e51d9",25,"d16aa",26,"69e56",27,"8cf16",28,"5493f",29,"4664a",30,"56d77",99,"42b5c",31,"3819b",32,"0f1ea",33,"91833",34,"9c36f",35,"4ed21",36,"456c7",37,"6e136",38,"43061",39,"42cca",40,"315c3",41,"ec9d8",104,"178e7",105,"1b2a2",42,"bf222",43,"b01f3",44,"9bd7d",45,"39a85",46,"8b331",47,"b08bc",48,"220b1",112,"f3a56",49,"80513",50,"ee48d",51,"223f3",52,"7df52",53,"518ff",54,"c7a54",55,"26ae4",56,"cc22e",57,"20dfd",58,"32064",59,"44a36",60,"06976",123,"841f5",61,"62c5c",125,"3880e",62,"6a3cb",63,"03615",64,"43fe0",65,"db5ad",132,"1ce3a",66,"4bc6b",67,"7efc0",68,"c8651",69,"90e4c",70,"21f7b",71,"b43ae"]}}