[1,["beQOIjtyVKx7QaQFUakmR7","44Vr9blAJHYZDnhMDcpxtB"],["spriteFrame","_textureSetter"],["cc.SpriteFrame",["cc.BitmapFont",["_name","fontSize","_fntConfig"],0]],[[1,0,1,2,4]],[[[[0,"bjl_yingdian_01",10,{"commonHeight":52,"fontSize":10,"atlasName":"bjl_yingdian_01.png","fontDefDictionary":{"32":{"xOffset":0,"yOffset":0,"xAdvance":44,"rect":{"x":325,"y":0,"width":48,"height":52}},"48":{"xOffset":0,"yOffset":0,"xAdvance":26,"rect":{"x":0,"y":0,"width":30,"height":52}},"49":{"xOffset":0,"yOffset":0,"xAdvance":15,"rect":{"x":30,"y":0,"width":19,"height":52}},"50":{"xOffset":0,"yOffset":0,"xAdvance":23,"rect":{"x":49,"y":0,"width":27,"height":52}},"51":{"xOffset":0,"yOffset":0,"xAdvance":22,"rect":{"x":76,"y":0,"width":26,"height":52}},"52":{"xOffset":0,"yOffset":0,"xAdvance":27,"rect":{"x":102,"y":0,"width":31,"height":52}},"53":{"xOffset":0,"yOffset":0,"xAdvance":23,"rect":{"x":133,"y":0,"width":27,"height":52}},"54":{"xOffset":0,"yOffset":0,"xAdvance":26,"rect":{"x":160,"y":0,"width":30,"height":52}},"55":{"xOffset":0,"yOffset":0,"xAdvance":25,"rect":{"x":190,"y":0,"width":29,"height":52}},"56":{"xOffset":0,"yOffset":0,"xAdvance":25,"rect":{"x":219,"y":0,"width":29,"height":52}},"57":{"xOffset":0,"yOffset":0,"xAdvance":25,"rect":{"x":248,"y":0,"width":29,"height":52}},"28857":{"xOffset":0,"yOffset":0,"xAdvance":44,"rect":{"x":277,"y":0,"width":48,"height":52}}},"kerningDict":{}}]],0,0,[0],[0],[0]],[[{"name":"bjl_yingdian_01","rect":[0,0,325,52],"offset":[-24,0],"originalSize":[373,52],"capInsets":[0,0,0,0]}],[0],0,[0],[1],[1]]]]