[1,["d8IgnyH8RLP4dves2pRYe+","ecK5L2f+RKbYqvHB+bABde","d3rXf4Rz9JL5TKiaCUuSeE","9f21rbeJdMOKAKMBuYj9ZK","1c7CwXYZlBlrJY+WBtlj8T","cdjPgT6+pO8aGJx6dGYcDd","bfmTvRX7RNyowX6zzomFi4","f0PHkAfW5DaKX/VPZ5hBuQ","2dJMfHRE5IMZ0I1dP8eFyO","c1/Yzb1n9OUoyhpna/WF4q","5ddbSwKXVIO7sv9Ki63bmf","67K3p80UxO67cHJD4HzPx0","55cSd4xBdJtYD4hT8T+X9E","1dauXt9EpCE6wTh6Hlz26K","f49fZtou9A57HDzXERFS1B","24T+qAazdLTqulaWSjMPeF","04IB2smgZLVKRmHnhLpp58","ffgbUn+I5Cp7UCLjdP4Dc0","cfr5nEmpZNDKMjXBnCllcH","f1zYFWgINGi5p4tTQjYiyJ","dbwJ7LqO9MoZAg/oTMVLt8"],["_textureSetter","zzz0002","zzz0004","zzz0006","zzz0008","zzz0010","zzz0012","zzz0014","zzz0017","zzz0019","zzz0021","zzz0023","zzz0025","zzz0027","zzz0029","zzz0031","zzz0033","zzz0035","zzz0037","zzz0039","zzz0041"],["cc.SpriteFrame",["cc.SpriteAtlas",["_name","_spriteFrames"],2,11]],[[1,0,1,2]],[[[{"name":"zzz0033","rect":[160,38,23,26],"offset":[-4,0],"originalSize":[65,56],"capInsets":[0,0,0,0]}],[0],0,[0],[0],[0]],[[[0,"zzz-dingpao_buyu0.plist",[{},"zzz0002",6,0,"zzz0004",6,1,"zzz0006",6,2,"zzz0008",6,3,"zzz0010",6,4,"zzz0012",6,5,"zzz0014",6,6,"zzz0017",6,7,"zzz0019",6,8,"zzz0021",6,9,"zzz0023",6,10,"zzz0025",6,11,"zzz0027",6,12,"zzz0029",6,13,"zzz0031",6,14,"zzz0033",6,15,"zzz0035",6,16,"zzz0037",6,17,"zzz0039",6,18,"zzz0041",6,19]]],0,0,[0,0,0,0,0,0,0,0,0,0,0,0,0,0,0,0,0,0,0,0],[1,2,3,4,5,6,7,8,9,10,11,12,13,14,15,16,17,18,19,20],[1,2,3,4,5,6,7,8,9,10,11,12,13,14,15,16,17,18,19,20]],[[{"name":"zzz0008","rect":[176,66,21,22],"offset":[-14,-8],"originalSize":[65,56],"capInsets":[0,0,0,0]}],[0],0,[0],[0],[0]],[[{"name":"zzz0027","rect":[43,54,39,40],"offset":[-3,1],"originalSize":[65,56],"capInsets":[0,0,0,0]}],[0],0,[0],[0],[0]],[[{"name":"zzz0031","rect":[162,2,23,24],"offset":[-8,-3],"originalSize":[65,56],"capInsets":[0,0,0,0]}],[0],0,[0],[0],[0]],[[{"name":"zzz0017","rect":[108,84,33,36],"offset":[-5,-1],"originalSize":[65,56],"capInsets":[0,0,0,0]}],[0],0,[0],[0],[0]],[[{"name":"zzz0025","rect":[51,2,39,40],"offset":[-7,-2],"originalSize":[65,56],"capInsets":[0,0,0,0]}],[0],0,[0],[0],[0]],[[{"name":"zzz0021","rect":[2,2,47,50],"offset":[-7,-2],"originalSize":[65,56],"capInsets":[0,0,0,0]}],[0],0,[0],[0],[0]],[[{"name":"zzz0023","rect":[84,44,39,38],"offset":[-10,-5],"originalSize":[65,56],"capInsets":[0,0,0,0]}],[0],0,[0],[0],[0]],[[{"name":"zzz0006","rect":[185,28,19,20],"offset":[-17,-12],"originalSize":[65,56],"capInsets":[0,0,0,0]}],[0],0,[0],[0],[0]],[[{"name":"zzz0012","rect":[129,2,31,34],"offset":[-13,-7],"originalSize":[65,56],"capInsets":[0,0,0,0]}],[0],0,[0],[0],[0]],[[{"name":"zzz0019","rect":[92,2,35,36],"offset":[-3,2],"originalSize":[65,56],"capInsets":[0,0,0,0]}],[0],0,[0],[0],[0]],[[{"name":"zzz0010","rect":[143,76,31,32],"offset":[-16,-11],"originalSize":[65,56],"capInsets":[0,0,0,0]}],[0],0,[0],[0],[0]],[[{"name":"zzz0037","rect":[29,96,25,28],"offset":[1,6],"originalSize":[65,56],"capInsets":[0,0,0,0]}],[0],0,[0],[0],[0]],[[{"name":"zzz0004","rect":[187,2,19,20],"offset":[-20,-14],"originalSize":[65,56],"capInsets":[0,0,0,0]}],[0],0,[0],[0],[0]],[[{"name":"zzz0041","rect":[83,96,23,26],"offset":[8,12],"originalSize":[65,56],"capInsets":[0,0,0,0]}],[0],0,[0],[0],[0]],[[{"name":"zzz0002","rect":[176,90,17,18],"offset":[-22,-18],"originalSize":[65,56],"capInsets":[0,0,0,0]}],[0],0,[0],[0],[0]],[[{"name":"zzz0014","rect":[125,40,33,34],"offset":[-10,-5],"originalSize":[65,56],"capInsets":[0,0,0,0]}],[0],0,[0],[0],[0]],[[{"name":"zzz0039","rect":[2,96,25,28],"offset":[5,8],"originalSize":[65,56],"capInsets":[0,0,0,0]}],[0],0,[0],[0],[0]],[[{"name":"zzz0029","rect":[2,54,39,40],"offset":[-1,3],"originalSize":[65,56],"capInsets":[0,0,0,0]}],[0],0,[0],[0],[0]],[[{"name":"zzz0035","rect":[56,96,25,26],"offset":[-2,2],"originalSize":[65,56],"capInsets":[0,0,0,0]}],[0],0,[0],[0],[0]]]]