[1,["4fMd8SZUBE7KXkWMv/0yc7","e6z4Iqx/FKOqd+G+nz45Po"],["spriteFrame","_textureSetter"],["cc.SpriteFrame",["cc.BitmapFont",["_name","fontSize","_fntConfig"],0]],[[1,0,1,2,4]],[[[[0,"zhs-nnjb-25",25,{"commonHeight":31,"fontSize":25,"atlasName":"zhs-nnjb-25.png","fontDefDictionary":{"32":{"xOffset":0,"yOffset":24,"xAdvance":9,"rect":{"x":0,"y":0,"width":0,"height":0}},"44":{"xOffset":-2,"yOffset":19,"xAdvance":9,"rect":{"x":230,"y":0,"width":10,"height":10}},"46":{"xOffset":0,"yOffset":19,"xAdvance":9,"rect":{"x":240,"y":0,"width":8,"height":7}},"47":{"xOffset":-1,"yOffset":4,"xAdvance":12,"rect":{"x":55,"y":0,"width":13,"height":22}},"48":{"xOffset":-1,"yOffset":4,"xAdvance":16,"rect":{"x":136,"y":0,"width":17,"height":22}},"49":{"xOffset":-1,"yOffset":5,"xAdvance":11,"rect":{"x":219,"y":0,"width":11,"height":20}},"50":{"xOffset":0,"yOffset":4,"xAdvance":16,"rect":{"x":186,"y":0,"width":16,"height":21}},"51":{"xOffset":-1,"yOffset":4,"xAdvance":16,"rect":{"x":119,"y":0,"width":17,"height":22}},"52":{"xOffset":-1,"yOffset":4,"xAdvance":16,"rect":{"x":169,"y":0,"width":17,"height":21}},"53":{"xOffset":-1,"yOffset":5,"xAdvance":16,"rect":{"x":153,"y":0,"width":16,"height":21}},"54":{"xOffset":-1,"yOffset":4,"xAdvance":16,"rect":{"x":102,"y":0,"width":17,"height":22}},"55":{"xOffset":-1,"yOffset":5,"xAdvance":15,"rect":{"x":202,"y":0,"width":17,"height":20}},"56":{"xOffset":-1,"yOffset":4,"xAdvance":16,"rect":{"x":85,"y":0,"width":17,"height":22}},"57":{"xOffset":-1,"yOffset":4,"xAdvance":16,"rect":{"x":68,"y":0,"width":17,"height":22}},"19975":{"xOffset":-1,"yOffset":3,"xAdvance":27,"rect":{"x":28,"y":0,"width":27,"height":25}},"20159":{"xOffset":-1,"yOffset":2,"xAdvance":27,"rect":{"x":0,"y":0,"width":28,"height":26}}},"kerningDict":{}}]],0,0,[0],[0],[0]],[[{"name":"zhs-nnjb-25","rect":[0,0,248,30],"offset":[-4,1],"originalSize":[256,32],"capInsets":[0,0,0,0]}],[0],0,[0],[1],[1]]]]